{"events":{"1040580":{"meta":{"id":"1040580","name":"巨人 vs DeNA","startDate":"2026-08-02T14:00:00.000+09:00","venue":"東京ドーム","region":"東京都","url":"https://ticketjam.jp/tickets/giants/event/1040580","teams":["giants","baystars"],"teamLabels":["読売ジャイアンツ","横浜DeNAベイスターズ"]},"snapshots":[{"t":"2026-07-19T03:46:39.844Z","all":{"count":114,"min":3500,"p25":4820,"median":6100,"max":100000},"one":{"count":41,"min":3500,"p25":4600,"median":6000,"max":35000}}]},"1040591":{"meta":{"id":"1040591","name":"ヤクルト vs 阪神","startDate":"2026-08-02T18:00:00.000+09:00","venue":"神宮球場","region":"東京都","url":"https://ticketjam.jp/tickets/yakult-swallows/event/1040591","teams":["yakult-swallows","hanshintigers"],"teamLabels":["東京ヤクルトスワローズ","阪神タイガース"]},"snapshots":[{"t":"2026-07-19T03:46:39.844Z","all":{"count":265,"min":1400,"p25":7500,"median":9000,"max":30000},"one":{"count":113,"min":1400,"p25":7000,"median":8900,"max":30000}}]},"1040629":{"meta":{"id":"1040629","name":"西武 vs オリックス","startDate":"2026-08-02T17:00:00.000+09:00","venue":"ベルーナドーム","region":"埼玉県","url":"https://ticketjam.jp/tickets/seibulions/event/1040629","teams":["seibulions","buffaloes"],"teamLabels":["埼玉西武ライオンズ","オリックス・バファローズ"]},"snapshots":[{"t":"2026-07-19T03:46:39.844Z","all":{"count":93,"min":1000,"p25":2800,"median":4200,"max":18000},"one":{"count":53,"min":1000,"p25":2900,"median":4200,"max":13500}}]},"1040646":{"meta":{"id":"1040646","name":"オリックス vs 楽天","startDate":"2026-08-03T18:00:00.000+09:00","venue":"東京ドーム","region":"東京都","url":"https://ticketjam.jp/tickets/buffaloes/event/1040646","teams":["buffaloes","rakuteneagles"],"teamLabels":["オリックス・バファローズ","東北楽天ゴールデンイーグルス"]},"snapshots":[{"t":"2026-07-19T03:46:39.844Z","all":{"count":53,"min":3200,"p25":8000,"median":11000,"max":59700},"one":{"count":32,"min":4500,"p25":8000,"median":14450,"max":59700}}]},"1040655":{"meta":{"id":"1040655","name":"DeNA vs 阪神","startDate":"2026-08-04T17:45:00.000+09:00","venue":"横浜スタジアム","region":"神奈川県","url":"https://ticketjam.jp/tickets/baystars/event/1040655","teams":["baystars","hanshintigers"],"teamLabels":["横浜DeNAベイスターズ","阪神タイガース"]},"snapshots":[{"t":"2026-07-19T03:46:39.844Z","all":{"count":181,"min":5000,"p25":7700,"median":10000,"max":30000},"one":{"count":57,"min":6000,"p25":8100,"median":10500,"max":26500}}]},"1040656":{"meta":{"id":"1040656","name":"DeNA vs 阪神","startDate":"2026-08-05T17:45:00.000+09:00","venue":"横浜スタジアム","region":"神奈川県","url":"https://ticketjam.jp/tickets/baystars/event/1040656","teams":["baystars","hanshintigers"],"teamLabels":["横浜DeNAベイスターズ","阪神タイガース"]},"snapshots":[{"t":"2026-07-19T03:46:39.844Z","all":{"count":180,"min":5000,"p25":7900,"median":10000,"max":39980},"one":{"count":55,"min":5300,"p25":7500,"median":9900,"max":38000}}]},"1040657":{"meta":{"id":"1040657","name":"DeNA vs 阪神","startDate":"2026-08-06T17:45:00.000+09:00","venue":"横浜スタジアム","region":"神奈川県","url":"https://ticketjam.jp/tickets/baystars/event/1040657","teams":["baystars","hanshintigers"],"teamLabels":["横浜DeNAベイスターズ","阪神タイガース"]},"snapshots":[{"t":"2026-07-19T03:46:39.844Z","all":{"count":201,"min":3000,"p25":7400,"median":9800,"max":56000},"one":{"count":50,"min":3000,"p25":8200,"median":10000,"max":56000}}]},"1040688":{"meta":{"id":"1040688","name":"ロッテ vs 西武","startDate":"2026-08-04T18:00:00.000+09:00","venue":"ZOZOマリンスタジアム（千葉マリンスタジアム）","region":"千葉県","url":"https://ticketjam.jp/tickets/marines/event/1040688","teams":["marines","seibulions"],"teamLabels":["千葉ロッテマリーンズ","埼玉西武ライオンズ"]},"snapshots":[{"t":"2026-07-19T03:46:39.844Z","all":{"count":26,"min":1100,"p25":1625,"median":2900,"max":22000},"one":{"count":20,"min":1100,"p25":1500,"median":2900,"max":10000}}]},"1040689":{"meta":{"id":"1040689","name":"ロッテ vs 西武","startDate":"2026-08-05T18:00:00.000+09:00","venue":"ZOZOマリンスタジアム（千葉マリンスタジアム）","region":"千葉県","url":"https://ticketjam.jp/tickets/marines/event/1040689","teams":["marines","seibulions"],"teamLabels":["千葉ロッテマリーンズ","埼玉西武ライオンズ"]},"snapshots":[{"t":"2026-07-19T03:46:39.844Z","all":{"count":38,"min":700,"p25":1500,"median":3095,"max":20000},"one":{"count":25,"min":1300,"p25":1999,"median":3900,"max":20000}}]}}}