{"fetchedAt":"2026-07-21T19:09:55.934Z","games":[{"id":"1040709","team":"giants","name":"巨人 vs ヤクルト","startDate":"2026-08-07T18:00:00.000+09:00","venue":"東京ドーム","region":"東京都","url":"https://ticketjam.jp/tickets/giants/event/1040709","path":"/tickets/giants/event/1040709","listingCount":80,"teams":["giants","yakult-swallows"]},{"id":"1040710","team":"giants","name":"巨人 vs ヤクルト","startDate":"2026-08-08T15:00:00.000+09:00","venue":"東京ドーム","region":"東京都","url":"https://ticketjam.jp/tickets/giants/event/1040710","path":"/tickets/giants/event/1040710","listingCount":83,"teams":["giants","yakult-swallows"]},{"id":"1040711","team":"giants","name":"巨人 vs ヤクルト","startDate":"2026-08-09T14:00:00.000+09:00","venue":"東京ドーム","region":"東京都","url":"https://ticketjam.jp/tickets/giants/event/1040711","path":"/tickets/giants/event/1040711","listingCount":127,"teams":["giants","yakult-swallows"]},{"id":"1040331","team":"giants","name":"ヤクルト vs 巨人","startDate":"2026-08-25T18:00:00.000+09:00","venue":"神宮球場","region":"東京都","url":"https://ticketjam.jp/tickets/yakult-swallows/event/1040331","path":"/tickets/giants/event/1040331","listingCount":27,"teams":["giants","yakult-swallows"]},{"id":"1040332","team":"giants","name":"ヤクルト vs 巨人","startDate":"2026-08-26T18:00:00.000+09:00","venue":"神宮球場","region":"東京都","url":"https://ticketjam.jp/tickets/yakult-swallows/event/1040332","path":"/tickets/giants/event/1040332","listingCount":31,"teams":["giants","yakult-swallows"]},{"id":"1040333","team":"giants","name":"ヤクルト vs 巨人","startDate":"2026-08-27T18:00:00.000+09:00","venue":"神宮球場","region":"東京都","url":"https://ticketjam.jp/tickets/yakult-swallows/event/1040333","path":"/tickets/giants/event/1040333","listingCount":51,"teams":["giants","yakult-swallows"]},{"id":"1040712","team":"giants","name":"巨人 vs ヤクルト","startDate":"2026-09-20T14:00:00.000+09:00","venue":"東京ドーム","region":"東京都","url":"https://ticketjam.jp/tickets/giants/event/1040712","path":"/tickets/giants/event/1040712","listingCount":30,"teams":["giants","yakult-swallows"]},{"id":"1040578","team":"giants","name":"巨人 vs DeNA","startDate":"2026-07-31T18:00:00.000+09:00","venue":"東京ドーム","region":"東京都","url":"https://ticketjam.jp/tickets/giants/event/1040578","path":"/tickets/giants/event/1040578","listingCount":155,"teams":["giants","baystars"]},{"id":"1040579","team":"giants","name":"巨人 vs DeNA","startDate":"2026-08-01T18:00:00.000+09:00","venue":"東京ドーム","region":"東京都","url":"https://ticketjam.jp/tickets/giants/event/1040579","path":"/tickets/giants/event/1040579","listingCount":193,"teams":["giants","baystars"]},{"id":"1040580","team":"giants","name":"巨人 vs DeNA","startDate":"2026-08-02T14:00:00.000+09:00","venue":"東京ドーム","region":"東京都","url":"https://ticketjam.jp/tickets/giants/event/1040580","path":"/tickets/giants/event/1040580","listingCount":121,"teams":["giants","baystars"]},{"id":"1040787","team":"giants","name":"DeNA vs 巨人","startDate":"2026-08-18T17:45:00.000+09:00","venue":"横浜スタジアム","region":"神奈川県","url":"https://ticketjam.jp/tickets/baystars/event/1040787","path":"/tickets/giants/event/1040787","listingCount":39,"teams":["giants","baystars"]},{"id":"1040788","team":"giants","name":"DeNA vs 巨人","startDate":"2026-08-19T17:45:00.000+09:00","venue":"横浜スタジアム","region":"神奈川県","url":"https://ticketjam.jp/tickets/baystars/event/1040788","path":"/tickets/giants/event/1040788","listingCount":44,"teams":["giants","baystars"]},{"id":"1040789","team":"giants","name":"DeNA vs 巨人","startDate":"2026-08-20T17:45:00.000+09:00","venue":"横浜スタジアム","region":"神奈川県","url":"https://ticketjam.jp/tickets/baystars/event/1040789","path":"/tickets/giants/event/1040789","listingCount":42,"teams":["giants","baystars"]},{"id":"1040581","team":"giants","name":"巨人 vs DeNA","startDate":"2026-09-01T18:00:00.000+09:00","venue":"京セラドーム大阪","region":"大阪府","url":"https://ticketjam.jp/tickets/giants/event/1040581","path":"/tickets/giants/event/1040581","listingCount":76,"teams":["giants","baystars"]},{"id":"1040582","team":"giants","name":"巨人 vs DeNA","startDate":"2026-09-02T18:00:00.000+09:00","venue":"京セラドーム大阪","region":"大阪府","url":"https://ticketjam.jp/tickets/giants/event/1040582","path":"/tickets/giants/event/1040582","listingCount":69,"teams":["giants","baystars"]},{"id":"1040790","team":"giants","name":"DeNA vs 巨人","startDate":"2026-09-13T18:00:00.000+09:00","venue":"横浜スタジアム","region":"神奈川県","url":"https://ticketjam.jp/tickets/baystars/event/1040790","path":"/tickets/giants/event/1040790","listingCount":41,"teams":["giants","baystars"]},{"id":"1226615","team":"giants","name":"DeNA vs 巨人","startDate":"2026-09-14T18:00:00.000+09:00","venue":"横浜スタジアム","region":"神奈川県","url":"https://ticketjam.jp/tickets/baystars/event/1226615","path":"/tickets/giants/event/1226615","listingCount":15,"teams":["giants","baystars"]},{"id":"1040771","team":"giants","name":"中日 vs 巨人","startDate":"2026-08-14T18:00:00.000+09:00","venue":"バンテリンドーム ナゴヤ","region":"愛知県","url":"https://ticketjam.jp/tickets/dragons/event/1040771","path":"/tickets/giants/event/1040771","listingCount":75,"teams":["giants","dragons"]},{"id":"1040772","team":"giants","name":"中日 vs 巨人","startDate":"2026-08-15T14:00:00.000+09:00","venue":"バンテリンドーム ナゴヤ","region":"愛知県","url":"https://ticketjam.jp/tickets/dragons/event/1040772","path":"/tickets/giants/event/1040772","listingCount":113,"teams":["giants","dragons"]},{"id":"1040773","team":"giants","name":"中日 vs 巨人","startDate":"2026-08-16T13:30:00.000+09:00","venue":"バンテリンドーム ナゴヤ","region":"愛知県","url":"https://ticketjam.jp/tickets/dragons/event/1040773","path":"/tickets/giants/event/1040773","listingCount":119,"teams":["giants","dragons"]},{"id":"1040396","team":"giants","name":"巨人 vs 中日","startDate":"2026-09-08T18:00:00.000+09:00","venue":"東京ドーム","region":"東京都","url":"https://ticketjam.jp/tickets/giants/event/1040396","path":"/tickets/giants/event/1040396","listingCount":44,"teams":["giants","dragons"]},{"id":"1040397","team":"giants","name":"巨人 vs 中日","startDate":"2026-09-09T18:00:00.000+09:00","venue":"東京ドーム","region":"東京都","url":"https://ticketjam.jp/tickets/giants/event/1040397","path":"/tickets/giants/event/1040397","listingCount":56,"teams":["giants","dragons"]},{"id":"1040398","team":"giants","name":"巨人 vs 中日","startDate":"2026-09-10T18:00:00.000+09:00","venue":"東京ドーム","region":"東京都","url":"https://ticketjam.jp/tickets/giants/event/1040398","path":"/tickets/giants/event/1040398","listingCount":56,"teams":["giants","dragons"]},{"id":"1040399","team":"giants","name":"巨人 vs 中日","startDate":"2026-09-18T18:00:00.000+09:00","venue":"東京ドーム","region":"東京都","url":"https://ticketjam.jp/tickets/giants/event/1040399","path":"/tickets/giants/event/1040399","listingCount":31,"teams":["giants","dragons"]},{"id":"1040400","team":"giants","name":"巨人 vs 中日","startDate":"2026-09-19T14:00:00.000+09:00","venue":"東京ドーム","region":"東京都","url":"https://ticketjam.jp/tickets/giants/event/1040400","path":"/tickets/giants/event/1040400","listingCount":32,"teams":["giants","dragons"]},{"id":"1036338","team":"giants","name":"阪神 vs 巨人","startDate":"2026-07-24T18:00:00.000+09:00","venue":"阪神甲子園球場","region":"兵庫県","url":"https://ticketjam.jp/tickets/hanshintigers/event/1036338","path":"/tickets/giants/event/1036338","listingCount":73,"teams":["giants","hanshintigers"]},{"id":"1036339","team":"giants","name":"阪神 vs 巨人","startDate":"2026-07-25T18:00:00.000+09:00","venue":"阪神甲子園球場","region":"兵庫県","url":"https://ticketjam.jp/tickets/hanshintigers/event/1036339","path":"/tickets/giants/event/1036339","listingCount":82,"teams":["giants","hanshintigers"]},{"id":"1036350","team":"giants","name":"阪神 vs 巨人","startDate":"2026-07-26T18:00:00.000+09:00","venue":"阪神甲子園球場","region":"兵庫県","url":"https://ticketjam.jp/tickets/hanshintigers/event/1036350","path":"/tickets/giants/event/1036350","listingCount":175,"teams":["giants","hanshintigers"]},{"id":"1040742","team":"giants","name":"巨人 vs 阪神","startDate":"2026-08-11T14:00:00.000+09:00","venue":"東京ドーム","region":"東京都","url":"https://ticketjam.jp/tickets/giants/event/1040742","path":"/tickets/giants/event/1040742","listingCount":167,"teams":["giants","hanshintigers"]},{"id":"1040743","team":"giants","name":"巨人 vs 阪神","startDate":"2026-08-12T18:00:00.000+09:00","venue":"東京ドーム","region":"東京都","url":"https://ticketjam.jp/tickets/giants/event/1040743","path":"/tickets/giants/event/1040743","listingCount":258,"teams":["giants","hanshintigers"]},{"id":"1040744","team":"giants","name":"巨人 vs 阪神","startDate":"2026-08-13T18:00:00.000+09:00","venue":"東京ドーム","region":"東京都","url":"https://ticketjam.jp/tickets/giants/event/1040744","path":"/tickets/giants/event/1040744","listingCount":317,"teams":["giants","hanshintigers"]},{"id":"1040562","team":"giants","name":"阪神 vs 巨人","startDate":"2026-08-28T18:00:00.000+09:00","venue":"阪神甲子園球場","region":"兵庫県","url":"https://ticketjam.jp/tickets/hanshintigers/event/1040562","path":"/tickets/giants/event/1040562","listingCount":139,"teams":["giants","hanshintigers"]},{"id":"1040563","team":"giants","name":"阪神 vs 巨人","startDate":"2026-08-29T18:00:00.000+09:00","venue":"阪神甲子園球場","region":"兵庫県","url":"https://ticketjam.jp/tickets/hanshintigers/event/1040563","path":"/tickets/giants/event/1040563","listingCount":105,"teams":["giants","hanshintigers"]},{"id":"1040564","team":"giants","name":"阪神 vs 巨人","startDate":"2026-08-30T18:00:00.000+09:00","venue":"阪神甲子園球場","region":"兵庫県","url":"https://ticketjam.jp/tickets/hanshintigers/event/1040564","path":"/tickets/giants/event/1040564","listingCount":189,"teams":["giants","hanshintigers"]},{"id":"1040745","team":"giants","name":"巨人 vs 阪神","startDate":"2026-09-12T14:00:00.000+09:00","venue":"東京ドーム","region":"東京都","url":"https://ticketjam.jp/tickets/giants/event/1040745","path":"/tickets/giants/event/1040745","listingCount":50,"teams":["giants","hanshintigers"]},{"id":"1040452","team":"giants","name":"巨人 vs 広島","startDate":"2026-07-21T18:00:00.000+09:00","venue":"東京ドーム","region":"東京都","url":"https://ticketjam.jp/tickets/giants/event/1040452","path":"/tickets/giants/event/1040452","listingCount":79,"teams":["giants","carp"]},{"id":"1040453","team":"giants","name":"巨人 vs 広島","startDate":"2026-07-22T18:00:00.000+09:00","venue":"東京ドーム","region":"東京都","url":"https://ticketjam.jp/tickets/giants/event/1040453","path":"/tickets/giants/event/1040453","listingCount":262,"teams":["giants","carp"]},{"id":"1040677","team":"giants","name":"広島 vs 巨人","startDate":"2026-08-04T18:00:00.000+09:00","venue":"MAZDA Zoom-Zoom スタジアム 広島","region":"広島県","url":"https://ticketjam.jp/tickets/carp/event/1040677","path":"/tickets/giants/event/1040677","listingCount":63,"teams":["giants","carp"]},{"id":"1040678","team":"giants","name":"広島 vs 巨人","startDate":"2026-08-05T18:00:00.000+09:00","venue":"MAZDA Zoom-Zoom スタジアム 広島","region":"広島県","url":"https://ticketjam.jp/tickets/carp/event/1040678","path":"/tickets/giants/event/1040678","listingCount":65,"teams":["giants","carp"]},{"id":"1040679","team":"giants","name":"広島 vs 巨人","startDate":"2026-08-06T18:00:00.000+09:00","venue":"MAZDA Zoom-Zoom スタジアム 広島","region":"広島県","url":"https://ticketjam.jp/tickets/carp/event/1040679","path":"/tickets/giants/event/1040679","listingCount":63,"teams":["giants","carp"]},{"id":"1040454","team":"giants","name":"巨人 vs 広島","startDate":"2026-08-21T18:00:00.000+09:00","venue":"東京ドーム","region":"東京都","url":"https://ticketjam.jp/tickets/giants/event/1040454","path":"/tickets/giants/event/1040454","listingCount":122,"teams":["giants","carp"]},{"id":"1040455","team":"giants","name":"巨人 vs 広島","startDate":"2026-08-22T14:00:00.000+09:00","venue":"東京ドーム","region":"東京都","url":"https://ticketjam.jp/tickets/giants/event/1040455","path":"/tickets/giants/event/1040455","listingCount":107,"teams":["giants","carp"]},{"id":"1040456","team":"giants","name":"巨人 vs 広島","startDate":"2026-08-23T14:00:00.000+09:00","venue":"東京ドーム","region":"東京都","url":"https://ticketjam.jp/tickets/giants/event/1040456","path":"/tickets/giants/event/1040456","listingCount":148,"teams":["giants","carp"]},{"id":"1040680","team":"giants","name":"広島 vs 巨人","startDate":"2026-09-04T18:00:00.000+09:00","venue":"MAZDA Zoom-Zoom スタジアム 広島","region":"広島県","url":"https://ticketjam.jp/tickets/carp/event/1040680","path":"/tickets/giants/event/1040680","listingCount":20,"teams":["giants","carp"]},{"id":"1040681","team":"giants","name":"広島 vs 巨人","startDate":"2026-09-05T18:00:00.000+09:00","venue":"MAZDA Zoom-Zoom スタジアム 広島","region":"広島県","url":"https://ticketjam.jp/tickets/carp/event/1040681","path":"/tickets/giants/event/1040681","listingCount":31,"teams":["giants","carp"]},{"id":"1040682","team":"giants","name":"広島 vs 巨人","startDate":"2026-09-06T18:00:00.000+09:00","venue":"MAZDA Zoom-Zoom スタジアム 広島","region":"広島県","url":"https://ticketjam.jp/tickets/carp/event/1040682","path":"/tickets/giants/event/1040682","listingCount":53,"teams":["giants","carp"]},{"id":"1040683","team":"giants","name":"広島 vs 巨人","startDate":"2026-09-22T15:00:00.000+09:00","venue":"MAZDA Zoom-Zoom スタジアム 広島","region":"広島県","url":"https://ticketjam.jp/tickets/carp/event/1040683","path":"/tickets/giants/event/1040683","listingCount":27,"teams":["giants","carp"]},{"id":"1040684","team":"giants","name":"広島 vs 巨人","startDate":"2026-09-23T15:00:00.000+09:00","venue":"MAZDA Zoom-Zoom スタジアム 広島","region":"広島県","url":"https://ticketjam.jp/tickets/carp/event/1040684","path":"/tickets/giants/event/1040684","listingCount":48,"teams":["giants","carp"]},{"id":"1226613","team":"giants","name":"広島 vs 巨人","startDate":"2026-09-24T18:00:00.000+09:00","venue":"MAZDA Zoom-Zoom スタジアム 広島","region":"広島県","url":"https://ticketjam.jp/tickets/carp/event/1226613","path":"/tickets/giants/event/1226613","listingCount":21,"teams":["giants","carp"]},{"id":"1040767","team":"yakult-swallows","name":"ヤクルト vs DeNA","startDate":"2026-08-14T18:00:00.000+09:00","venue":"神宮球場","region":"東京都","url":"https://ticketjam.jp/tickets/yakult-swallows/event/1040767","path":"/tickets/yakult-swallows/event/1040767","listingCount":44,"teams":["yakult-swallows","baystars"]},{"id":"1040768","team":"yakult-swallows","name":"ヤクルト vs DeNA","startDate":"2026-08-15T18:00:00.000+09:00","venue":"神宮球場","region":"東京都","url":"https://ticketjam.jp/tickets/yakult-swallows/event/1040768","path":"/tickets/yakult-swallows/event/1040768","listingCount":70,"teams":["yakult-swallows","baystars"]},{"id":"1040769","team":"yakult-swallows","name":"ヤクルト vs DeNA","startDate":"2026-08-16T18:00:00.000+09:00","venue":"神宮球場","region":"東京都","url":"https://ticketjam.jp/tickets/yakult-swallows/event/1040769","path":"/tickets/yakult-swallows/event/1040769","listingCount":59,"teams":["yakult-swallows","baystars"]},{"id":"1040405","team":"yakult-swallows","name":"DeNA vs ヤクルト","startDate":"2026-09-08T18:00:00.000+09:00","venue":"横浜スタジアム","region":"神奈川県","url":"https://ticketjam.jp/tickets/baystars/event/1040405","path":"/tickets/yakult-swallows/event/1040405","listingCount":17,"teams":["yakult-swallows","baystars"]},{"id":"1040406","team":"yakult-swallows","name":"DeNA vs ヤクルト","startDate":"2026-09-09T18:00:00.000+09:00","venue":"横浜スタジアム","region":"神奈川県","url":"https://ticketjam.jp/tickets/baystars/event/1040406","path":"/tickets/yakult-swallows/event/1040406","listingCount":15,"teams":["yakult-swallows","baystars"]},{"id":"1040407","team":"yakult-swallows","name":"DeNA vs ヤクルト","startDate":"2026-09-10T18:00:00.000+09:00","venue":"横浜スタジアム","region":"神奈川県","url":"https://ticketjam.jp/tickets/baystars/event/1040407","path":"/tickets/yakult-swallows/event/1040407","listingCount":24,"teams":["yakult-swallows","baystars"]},{"id":"1040408","team":"yakult-swallows","name":"DeNA vs ヤクルト","startDate":"2026-09-18T18:00:00.000+09:00","venue":"横浜スタジアム","region":"神奈川県","url":"https://ticketjam.jp/tickets/baystars/event/1040408","path":"/tickets/yakult-swallows/event/1040408","listingCount":19,"teams":["yakult-swallows","baystars"]},{"id":"1040409","team":"yakult-swallows","name":"DeNA vs ヤクルト","startDate":"2026-09-19T18:00:00.000+09:00","venue":"横浜スタジアム","region":"神奈川県","url":"https://ticketjam.jp/tickets/baystars/event/1040409","path":"/tickets/yakult-swallows/event/1040409","listingCount":30,"teams":["yakult-swallows","baystars"]},{"id":"1040466","team":"yakult-swallows","name":"ヤクルト vs 中日","startDate":"2026-07-21T18:00:00.000+09:00","venue":"神宮球場","region":"東京都","url":"https://ticketjam.jp/tickets/yakult-swallows/event/1040466","path":"/tickets/yakult-swallows/event/1040466","listingCount":89,"teams":["yakult-swallows","dragons"]},{"id":"1040467","team":"yakult-swallows","name":"ヤクルト vs 中日","startDate":"2026-07-22T18:00:00.000+09:00","venue":"神宮球場","region":"東京都","url":"https://ticketjam.jp/tickets/yakult-swallows/event/1040467","path":"/tickets/yakult-swallows/event/1040467","listingCount":95,"teams":["yakult-swallows","dragons"]},{"id":"1040668","team":"yakult-swallows","name":"中日 vs ヤクルト","startDate":"2026-08-04T18:00:00.000+09:00","venue":"バンテリンドーム ナゴヤ","region":"愛知県","url":"https://ticketjam.jp/tickets/dragons/event/1040668","path":"/tickets/yakult-swallows/event/1040668","listingCount":80,"teams":["yakult-swallows","dragons"]},{"id":"1040669","team":"yakult-swallows","name":"中日 vs ヤクルト","startDate":"2026-08-05T18:00:00.000+09:00","venue":"バンテリンドーム ナゴヤ","region":"愛知県","url":"https://ticketjam.jp/tickets/dragons/event/1040669","path":"/tickets/yakult-swallows/event/1040669","listingCount":94,"teams":["yakult-swallows","dragons"]},{"id":"1040670","team":"yakult-swallows","name":"中日 vs ヤクルト","startDate":"2026-08-06T18:00:00.000+09:00","venue":"バンテリンドーム ナゴヤ","region":"愛知県","url":"https://ticketjam.jp/tickets/dragons/event/1040670","path":"/tickets/yakult-swallows/event/1040670","listingCount":57,"teams":["yakult-swallows","dragons"]},{"id":"1040671","team":"yakult-swallows","name":"中日 vs ヤクルト","startDate":"2026-08-21T18:00:00.000+09:00","venue":"バンテリンドーム ナゴヤ","region":"愛知県","url":"https://ticketjam.jp/tickets/dragons/event/1040671","path":"/tickets/yakult-swallows/event/1040671","listingCount":30,"teams":["yakult-swallows","dragons"]},{"id":"1040672","team":"yakult-swallows","name":"中日 vs ヤクルト","startDate":"2026-08-22T14:00:00.000+09:00","venue":"バンテリンドーム ナゴヤ","region":"愛知県","url":"https://ticketjam.jp/tickets/dragons/event/1040672","path":"/tickets/yakult-swallows/event/1040672","listingCount":41,"teams":["yakult-swallows","dragons"]},{"id":"1040673","team":"yakult-swallows","name":"中日 vs ヤクルト","startDate":"2026-08-23T13:30:00.000+09:00","venue":"バンテリンドーム ナゴヤ","region":"愛知県","url":"https://ticketjam.jp/tickets/dragons/event/1040673","path":"/tickets/yakult-swallows/event/1040673","listingCount":69,"teams":["yakult-swallows","dragons"]},{"id":"1040468","team":"yakult-swallows","name":"ヤクルト vs 中日","startDate":"2026-09-04T18:00:00.000+09:00","venue":"神宮球場","region":"東京都","url":"https://ticketjam.jp/tickets/yakult-swallows/event/1040468","path":"/tickets/yakult-swallows/event/1040468","listingCount":17,"teams":["yakult-swallows","dragons"]},{"id":"1040469","team":"yakult-swallows","name":"ヤクルト vs 中日","startDate":"2026-09-05T18:00:00.000+09:00","venue":"神宮球場","region":"東京都","url":"https://ticketjam.jp/tickets/yakult-swallows/event/1040469","path":"/tickets/yakult-swallows/event/1040469","listingCount":19,"teams":["yakult-swallows","dragons"]},{"id":"1040470","team":"yakult-swallows","name":"ヤクルト vs 中日","startDate":"2026-09-06T17:00:00.000+09:00","venue":"神宮球場","region":"東京都","url":"https://ticketjam.jp/tickets/yakult-swallows/event/1040470","path":"/tickets/yakult-swallows/event/1040470","listingCount":16,"teams":["yakult-swallows","dragons"]},{"id":"1040674","team":"yakult-swallows","name":"中日 vs ヤクルト","startDate":"2026-09-12T14:00:00.000+09:00","venue":"バンテリンドーム ナゴヤ","region":"愛知県","url":"https://ticketjam.jp/tickets/dragons/event/1040674","path":"/tickets/yakult-swallows/event/1040674","listingCount":57,"teams":["yakult-swallows","dragons"]},{"id":"1040589","team":"yakult-swallows","name":"ヤクルト vs 阪神","startDate":"2026-07-31T18:00:00.000+09:00","venue":"神宮球場","region":"東京都","url":"https://ticketjam.jp/tickets/yakult-swallows/event/1040589","path":"/tickets/yakult-swallows/event/1040589","listingCount":157,"teams":["yakult-swallows","hanshintigers"]},{"id":"1040590","team":"yakult-swallows","name":"ヤクルト vs 阪神","startDate":"2026-08-01T18:00:00.000+09:00","venue":"神宮球場","region":"東京都","url":"https://ticketjam.jp/tickets/yakult-swallows/event/1040590","path":"/tickets/yakult-swallows/event/1040590","listingCount":181,"teams":["yakult-swallows","hanshintigers"]},{"id":"1040591","team":"yakult-swallows","name":"ヤクルト vs 阪神","startDate":"2026-08-02T18:00:00.000+09:00","venue":"神宮球場","region":"東京都","url":"https://ticketjam.jp/tickets/yakult-swallows/event/1040591","path":"/tickets/yakult-swallows/event/1040591","listingCount":259,"teams":["yakult-swallows","hanshintigers"]},{"id":"1040796","team":"yakult-swallows","name":"阪神 vs ヤクルト","startDate":"2026-08-18T18:00:00.000+09:00","venue":"京セラドーム大阪","region":"大阪府","url":"https://ticketjam.jp/tickets/hanshintigers/event/1040796","path":"/tickets/yakult-swallows/event/1040796","listingCount":161,"teams":["yakult-swallows","hanshintigers"]},{"id":"1040797","team":"yakult-swallows","name":"阪神 vs ヤクルト","startDate":"2026-08-19T18:00:00.000+09:00","venue":"京セラドーム大阪","region":"大阪府","url":"https://ticketjam.jp/tickets/hanshintigers/event/1040797","path":"/tickets/yakult-swallows/event/1040797","listingCount":170,"teams":["yakult-swallows","hanshintigers"]},{"id":"1040798","team":"yakult-swallows","name":"阪神 vs ヤクルト","startDate":"2026-08-20T18:00:00.000+09:00","venue":"京セラドーム大阪","region":"大阪府","url":"https://ticketjam.jp/tickets/hanshintigers/event/1040798","path":"/tickets/yakult-swallows/event/1040798","listingCount":180,"teams":["yakult-swallows","hanshintigers"]},{"id":"1040592","team":"yakult-swallows","name":"ヤクルト vs 阪神","startDate":"2026-09-01T18:00:00.000+09:00","venue":"神宮球場","region":"東京都","url":"https://ticketjam.jp/tickets/yakult-swallows/event/1040592","path":"/tickets/yakult-swallows/event/1040592","listingCount":90,"teams":["yakult-swallows","hanshintigers"]},{"id":"1040593","team":"yakult-swallows","name":"ヤクルト vs 阪神","startDate":"2026-09-02T18:00:00.000+09:00","venue":"神宮球場","region":"東京都","url":"https://ticketjam.jp/tickets/yakult-swallows/event/1040593","path":"/tickets/yakult-swallows/event/1040593","listingCount":102,"teams":["yakult-swallows","hanshintigers"]},{"id":"1040594","team":"yakult-swallows","name":"ヤクルト vs 阪神","startDate":"2026-09-03T18:00:00.000+09:00","venue":"神宮球場","region":"東京都","url":"https://ticketjam.jp/tickets/yakult-swallows/event/1040594","path":"/tickets/yakult-swallows/event/1040594","listingCount":81,"teams":["yakult-swallows","hanshintigers"]},{"id":"1040595","team":"yakult-swallows","name":"ヤクルト vs 阪神","startDate":"2026-09-22T18:00:00.000+09:00","venue":"神宮球場","region":"東京都","url":"https://ticketjam.jp/tickets/yakult-swallows/event/1040595","path":"/tickets/yakult-swallows/event/1040595","listingCount":104,"teams":["yakult-swallows","hanshintigers"]},{"id":"1040596","team":"yakult-swallows","name":"ヤクルト vs 阪神","startDate":"2026-09-23T14:00:00.000+09:00","venue":"神宮球場","region":"東京都","url":"https://ticketjam.jp/tickets/yakult-swallows/event/1040596","path":"/tickets/yakult-swallows/event/1040596","listingCount":91,"teams":["yakult-swallows","hanshintigers"]},{"id":"1040540","team":"yakult-swallows","name":"ヤクルト vs 広島","startDate":"2026-07-24T18:00:00.000+09:00","venue":"神宮球場","region":"東京都","url":"https://ticketjam.jp/tickets/yakult-swallows/event/1040540","path":"/tickets/yakult-swallows/event/1040540","listingCount":75,"teams":["yakult-swallows","carp"]},{"id":"1040541","team":"yakult-swallows","name":"ヤクルト vs 広島","startDate":"2026-07-25T18:00:00.000+09:00","venue":"神宮球場","region":"東京都","url":"https://ticketjam.jp/tickets/yakult-swallows/event/1040541","path":"/tickets/yakult-swallows/event/1040541","listingCount":90,"teams":["yakult-swallows","carp"]},{"id":"1040542","team":"yakult-swallows","name":"ヤクルト vs 広島","startDate":"2026-07-26T18:00:00.000+09:00","venue":"神宮球場","region":"東京都","url":"https://ticketjam.jp/tickets/yakult-swallows/event/1040542","path":"/tickets/yakult-swallows/event/1040542","listingCount":69,"teams":["yakult-swallows","carp"]},{"id":"1040543","team":"yakult-swallows","name":"ヤクルト vs 広島","startDate":"2026-08-11T18:00:00.000+09:00","venue":"神宮球場","region":"東京都","url":"https://ticketjam.jp/tickets/yakult-swallows/event/1040543","path":"/tickets/yakult-swallows/event/1040543","listingCount":75,"teams":["yakult-swallows","carp"]},{"id":"1040544","team":"yakult-swallows","name":"ヤクルト vs 広島","startDate":"2026-08-12T18:00:00.000+09:00","venue":"神宮球場","region":"東京都","url":"https://ticketjam.jp/tickets/yakult-swallows/event/1040544","path":"/tickets/yakult-swallows/event/1040544","listingCount":45,"teams":["yakult-swallows","carp"]},{"id":"1040545","team":"yakult-swallows","name":"ヤクルト vs 広島","startDate":"2026-08-13T18:00:00.000+09:00","venue":"神宮球場","region":"東京都","url":"https://ticketjam.jp/tickets/yakult-swallows/event/1040545","path":"/tickets/yakult-swallows/event/1040545","listingCount":49,"teams":["yakult-swallows","carp"]},{"id":"1040746","team":"yakult-swallows","name":"広島 vs ヤクルト","startDate":"2026-08-28T18:00:00.000+09:00","venue":"MAZDA Zoom-Zoom スタジアム 広島","region":"広島県","url":"https://ticketjam.jp/tickets/carp/event/1040746","path":"/tickets/yakult-swallows/event/1040746","listingCount":26,"teams":["yakult-swallows","carp"]},{"id":"1040747","team":"yakult-swallows","name":"広島 vs ヤクルト","startDate":"2026-08-29T18:00:00.000+09:00","venue":"MAZDA Zoom-Zoom スタジアム 広島","region":"広島県","url":"https://ticketjam.jp/tickets/carp/event/1040747","path":"/tickets/yakult-swallows/event/1040747","listingCount":36,"teams":["yakult-swallows","carp"]},{"id":"1040748","team":"yakult-swallows","name":"広島 vs ヤクルト","startDate":"2026-08-30T18:00:00.000+09:00","venue":"MAZDA Zoom-Zoom スタジアム 広島","region":"広島県","url":"https://ticketjam.jp/tickets/carp/event/1040748","path":"/tickets/yakult-swallows/event/1040748","listingCount":38,"teams":["yakult-swallows","carp"]},{"id":"1040546","team":"yakult-swallows","name":"ヤクルト vs 広島","startDate":"2026-09-13T18:00:00.000+09:00","venue":"神宮球場","region":"東京都","url":"https://ticketjam.jp/tickets/yakult-swallows/event/1040546","path":"/tickets/yakult-swallows/event/1040546","listingCount":17,"teams":["yakult-swallows","carp"]},{"id":"1139064","team":"yakult-swallows","name":"ヤクルト vs 広島","startDate":"2026-09-14T18:00:00.000+09:00","venue":"神宮球場","region":"東京都","url":"https://ticketjam.jp/tickets/yakult-swallows/event/1139064","path":"/tickets/yakult-swallows/event/1139064","listingCount":9,"teams":["yakult-swallows","carp"]},{"id":"1040553","team":"baystars","name":"中日 vs DeNA","startDate":"2026-07-24T18:00:00.000+09:00","venue":"バンテリンドーム ナゴヤ","region":"愛知県","url":"https://ticketjam.jp/tickets/dragons/event/1040553","path":"/tickets/baystars/event/1040553","listingCount":35,"teams":["baystars","dragons"]},{"id":"1040554","team":"baystars","name":"中日 vs DeNA","startDate":"2026-07-25T14:00:00.000+09:00","venue":"バンテリンドーム ナゴヤ","region":"愛知県","url":"https://ticketjam.jp/tickets/dragons/event/1040554","path":"/tickets/baystars/event/1040554","listingCount":76,"teams":["baystars","dragons"]},{"id":"1040555","team":"baystars","name":"中日 vs DeNA","startDate":"2026-07-26T13:30:00.000+09:00","venue":"バンテリンドーム ナゴヤ","region":"愛知県","url":"https://ticketjam.jp/tickets/dragons/event/1040555","path":"/tickets/baystars/event/1040555","listingCount":110,"teams":["baystars","dragons"]},{"id":"1040556","team":"baystars","name":"中日 vs DeNA","startDate":"2026-08-11T14:00:00.000+09:00","venue":"バンテリンドーム ナゴヤ","region":"愛知県","url":"https://ticketjam.jp/tickets/dragons/event/1040556","path":"/tickets/baystars/event/1040556","listingCount":44,"teams":["baystars","dragons"]},{"id":"1040557","team":"baystars","name":"中日 vs DeNA","startDate":"2026-08-12T18:00:00.000+09:00","venue":"バンテリンドーム ナゴヤ","region":"愛知県","url":"https://ticketjam.jp/tickets/dragons/event/1040557","path":"/tickets/baystars/event/1040557","listingCount":118,"teams":["baystars","dragons"]},{"id":"1040558","team":"baystars","name":"中日 vs DeNA","startDate":"2026-08-13T18:00:00.000+09:00","venue":"バンテリンドーム ナゴヤ","region":"愛知県","url":"https://ticketjam.jp/tickets/dragons/event/1040558","path":"/tickets/baystars/event/1040558","listingCount":86,"teams":["baystars","dragons"]},{"id":"1040749","team":"baystars","name":"DeNA vs 中日","startDate":"2026-08-28T18:00:00.000+09:00","venue":"横浜スタジアム","region":"神奈川県","url":"https://ticketjam.jp/tickets/baystars/event/1040749","path":"/tickets/baystars/event/1040749","listingCount":25,"teams":["baystars","dragons"]},{"id":"1040750","team":"baystars","name":"DeNA vs 中日","startDate":"2026-08-29T18:00:00.000+09:00","venue":"横浜スタジアム","region":"神奈川県","url":"https://ticketjam.jp/tickets/baystars/event/1040750","path":"/tickets/baystars/event/1040750","listingCount":49,"teams":["baystars","dragons"]},{"id":"1040751","team":"baystars","name":"DeNA vs 中日","startDate":"2026-08-30T18:00:00.000+09:00","venue":"横浜スタジアム","region":"神奈川県","url":"https://ticketjam.jp/tickets/baystars/event/1040751","path":"/tickets/baystars/event/1040751","listingCount":48,"teams":["baystars","dragons"]},{"id":"1040752","team":"baystars","name":"DeNA vs 中日","startDate":"2026-09-22T18:00:00.000+09:00","venue":"横浜スタジアム","region":"神奈川県","url":"https://ticketjam.jp/tickets/baystars/event/1040752","path":"/tickets/baystars/event/1040752","listingCount":32,"teams":["baystars","dragons"]},{"id":"1040753","team":"baystars","name":"DeNA vs 中日","startDate":"2026-09-23T18:00:00.000+09:00","venue":"横浜スタジアム","region":"神奈川県","url":"https://ticketjam.jp/tickets/baystars/event/1040753","path":"/tickets/baystars/event/1040753","listingCount":22,"teams":["baystars","dragons"]},{"id":"1040504","team":"baystars","name":"阪神 vs DeNA","startDate":"2026-07-21T18:00:00.000+09:00","venue":"阪神甲子園球場","region":"兵庫県","url":"https://ticketjam.jp/tickets/hanshintigers/event/1040504","path":"/tickets/baystars/event/1040504","listingCount":46,"teams":["baystars","hanshintigers"]},{"id":"1040505","team":"baystars","name":"阪神 vs DeNA","startDate":"2026-07-22T18:00:00.000+09:00","venue":"阪神甲子園球場","region":"兵庫県","url":"https://ticketjam.jp/tickets/hanshintigers/event/1040505","path":"/tickets/baystars/event/1040505","listingCount":58,"teams":["baystars","hanshintigers"]},{"id":"1040655","team":"baystars","name":"DeNA vs 阪神","startDate":"2026-08-04T17:45:00.000+09:00","venue":"横浜スタジアム","region":"神奈川県","url":"https://ticketjam.jp/tickets/baystars/event/1040655","path":"/tickets/baystars/event/1040655","listingCount":191,"teams":["baystars","hanshintigers"]},{"id":"1040656","team":"baystars","name":"DeNA vs 阪神","startDate":"2026-08-05T17:45:00.000+09:00","venue":"横浜スタジアム","region":"神奈川県","url":"https://ticketjam.jp/tickets/baystars/event/1040656","path":"/tickets/baystars/event/1040656","listingCount":194,"teams":["baystars","hanshintigers"]},{"id":"1040657","team":"baystars","name":"DeNA vs 阪神","startDate":"2026-08-06T17:45:00.000+09:00","venue":"横浜スタジアム","region":"神奈川県","url":"https://ticketjam.jp/tickets/baystars/event/1040657","path":"/tickets/baystars/event/1040657","listingCount":220,"teams":["baystars","hanshintigers"]},{"id":"1040658","team":"baystars","name":"DeNA vs 阪神","startDate":"2026-08-21T18:00:00.000+09:00","venue":"横浜スタジアム","region":"神奈川県","url":"https://ticketjam.jp/tickets/baystars/event/1040658","path":"/tickets/baystars/event/1040658","listingCount":129,"teams":["baystars","hanshintigers"]},{"id":"1040659","team":"baystars","name":"DeNA vs 阪神","startDate":"2026-08-22T18:00:00.000+09:00","venue":"横浜スタジアム","region":"神奈川県","url":"https://ticketjam.jp/tickets/baystars/event/1040659","path":"/tickets/baystars/event/1040659","listingCount":145,"teams":["baystars","hanshintigers"]},{"id":"1040660","team":"baystars","name":"DeNA vs 阪神","startDate":"2026-08-23T18:00:00.000+09:00","venue":"横浜スタジアム","region":"神奈川県","url":"https://ticketjam.jp/tickets/baystars/event/1040660","path":"/tickets/baystars/event/1040660","listingCount":232,"teams":["baystars","hanshintigers"]},{"id":"1040506","team":"baystars","name":"阪神 vs DeNA","startDate":"2026-09-05T18:00:00.000+09:00","venue":"阪神甲子園球場","region":"兵庫県","url":"https://ticketjam.jp/tickets/hanshintigers/event/1040506","path":"/tickets/baystars/event/1040506","listingCount":74,"teams":["baystars","hanshintigers"]},{"id":"1040507","team":"baystars","name":"阪神 vs DeNA","startDate":"2026-09-06T18:00:00.000+09:00","venue":"阪神甲子園球場","region":"兵庫県","url":"https://ticketjam.jp/tickets/hanshintigers/event/1040507","path":"/tickets/baystars/event/1040507","listingCount":107,"teams":["baystars","hanshintigers"]},{"id":"1040508","team":"baystars","name":"阪神 vs DeNA","startDate":"2026-09-20T18:00:00.000+09:00","venue":"阪神甲子園球場","region":"兵庫県","url":"https://ticketjam.jp/tickets/hanshintigers/event/1040508","path":"/tickets/baystars/event/1040508","listingCount":29,"teams":["baystars","hanshintigers"]},{"id":"1040509","team":"baystars","name":"阪神 vs DeNA","startDate":"2026-09-21T14:00:00.000+09:00","venue":"阪神甲子園球場","region":"兵庫県","url":"https://ticketjam.jp/tickets/hanshintigers/event/1040509","path":"/tickets/baystars/event/1040509","listingCount":12,"teams":["baystars","hanshintigers"]},{"id":"1040718","team":"baystars","name":"DeNA vs 広島","startDate":"2026-08-07T18:00:00.000+09:00","venue":"横浜スタジアム","region":"神奈川県","url":"https://ticketjam.jp/tickets/baystars/event/1040718","path":"/tickets/baystars/event/1040718","listingCount":49,"teams":["baystars","carp"]},{"id":"1040719","team":"baystars","name":"DeNA vs 広島","startDate":"2026-08-08T18:00:00.000+09:00","venue":"横浜スタジアム","region":"神奈川県","url":"https://ticketjam.jp/tickets/baystars/event/1040719","path":"/tickets/baystars/event/1040719","listingCount":98,"teams":["baystars","carp"]},{"id":"1040720","team":"baystars","name":"DeNA vs 広島","startDate":"2026-08-09T18:00:00.000+09:00","venue":"横浜スタジアム","region":"神奈川県","url":"https://ticketjam.jp/tickets/baystars/event/1040720","path":"/tickets/baystars/event/1040720","listingCount":54,"teams":["baystars","carp"]},{"id":"1040352","team":"baystars","name":"広島 vs DeNA","startDate":"2026-08-25T18:00:00.000+09:00","venue":"MAZDA Zoom-Zoom スタジアム 広島","region":"広島県","url":"https://ticketjam.jp/tickets/carp/event/1040352","path":"/tickets/baystars/event/1040352","listingCount":19,"teams":["baystars","carp"]},{"id":"1040353","team":"baystars","name":"広島 vs DeNA","startDate":"2026-08-26T18:00:00.000+09:00","venue":"MAZDA Zoom-Zoom スタジアム 広島","region":"広島県","url":"https://ticketjam.jp/tickets/carp/event/1040353","path":"/tickets/baystars/event/1040353","listingCount":28,"teams":["baystars","carp"]},{"id":"1040354","team":"baystars","name":"広島 vs DeNA","startDate":"2026-08-27T18:00:00.000+09:00","venue":"MAZDA Zoom-Zoom スタジアム 広島","region":"広島県","url":"https://ticketjam.jp/tickets/carp/event/1040354","path":"/tickets/baystars/event/1040354","listingCount":26,"teams":["baystars","carp"]},{"id":"1040355","team":"baystars","name":"広島 vs DeNA","startDate":"2026-09-11T18:00:00.000+09:00","venue":"MAZDA Zoom-Zoom スタジアム 広島","region":"広島県","url":"https://ticketjam.jp/tickets/carp/event/1040355","path":"/tickets/baystars/event/1040355","listingCount":18,"teams":["baystars","carp"]},{"id":"1040356","team":"baystars","name":"広島 vs DeNA","startDate":"2026-09-12T14:00:00.000+09:00","venue":"MAZDA Zoom-Zoom スタジアム 広島","region":"広島県","url":"https://ticketjam.jp/tickets/carp/event/1040356","path":"/tickets/baystars/event/1040356","listingCount":36,"teams":["baystars","carp"]},{"id":"1040612","team":"marines","name":"日本ハム vs ロッテ","startDate":"2026-07-31T18:00:00.000+09:00","venue":"エスコンフィールド北海道","region":"北海道","url":"https://ticketjam.jp/tickets/fighters/event/1040612","path":"/tickets/marines/event/1040612","listingCount":56,"teams":["marines","fighters"]},{"id":"1040158","team":"marines","name":"日本ハム vs ロッテ","startDate":"2026-08-01T14:00:00.000+09:00","venue":"エスコンフィールド北海道","region":"北海道","url":"https://ticketjam.jp/tickets/fighters/event/1040158","path":"/tickets/marines/event/1040158","listingCount":114,"teams":["marines","fighters"]},{"id":"1040159","team":"marines","name":"日本ハム vs ロッテ","startDate":"2026-08-02T13:00:00.000+09:00","venue":"エスコンフィールド北海道","region":"北海道","url":"https://ticketjam.jp/tickets/fighters/event/1040159","path":"/tickets/marines/event/1040159","listingCount":72,"teams":["marines","fighters"]},{"id":"1040820","team":"marines","name":"ロッテ vs 日本ハム","startDate":"2026-08-21T18:00:00.000+09:00","venue":"ZOZOマリンスタジアム（千葉マリンスタジアム）","region":"千葉県","url":"https://ticketjam.jp/tickets/marines/event/1040820","path":"/tickets/marines/event/1040820","listingCount":41,"teams":["marines","fighters"]},{"id":"1040821","team":"marines","name":"ロッテ vs 日本ハム","startDate":"2026-08-22T18:00:00.000+09:00","venue":"ZOZOマリンスタジアム（千葉マリンスタジアム）","region":"千葉県","url":"https://ticketjam.jp/tickets/marines/event/1040821","path":"/tickets/marines/event/1040821","listingCount":52,"teams":["marines","fighters"]},{"id":"1040822","team":"marines","name":"ロッテ vs 日本ハム","startDate":"2026-08-23T17:00:00.000+09:00","venue":"ZOZOマリンスタジアム（千葉マリンスタジアム）","region":"千葉県","url":"https://ticketjam.jp/tickets/marines/event/1040822","path":"/tickets/marines/event/1040822","listingCount":48,"teams":["marines","fighters"]},{"id":"1040160","team":"marines","name":"日本ハム vs ロッテ","startDate":"2026-08-28T18:00:00.000+09:00","venue":"エスコンフィールド北海道","region":"北海道","url":"https://ticketjam.jp/tickets/fighters/event/1040160","path":"/tickets/marines/event/1040160","listingCount":27,"teams":["marines","fighters"]},{"id":"1040161","team":"marines","name":"日本ハム vs ロッテ","startDate":"2026-08-29T14:00:00.000+09:00","venue":"エスコンフィールド北海道","region":"北海道","url":"https://ticketjam.jp/tickets/fighters/event/1040161","path":"/tickets/marines/event/1040161","listingCount":29,"teams":["marines","fighters"]},{"id":"1040162","team":"marines","name":"日本ハム vs ロッテ","startDate":"2026-08-30T13:00:00.000+09:00","venue":"エスコンフィールド北海道","region":"北海道","url":"https://ticketjam.jp/tickets/fighters/event/1040162","path":"/tickets/marines/event/1040162","listingCount":53,"teams":["marines","fighters"]},{"id":"1040614","team":"marines","name":"日本ハム vs ロッテ","startDate":"2026-09-15T18:00:00.000+09:00","venue":"エスコンフィールド北海道","region":"北海道","url":"https://ticketjam.jp/tickets/fighters/event/1040614","path":"/tickets/marines/event/1040614","listingCount":35,"teams":["marines","fighters"]},{"id":"1040823","team":"marines","name":"ロッテ vs 日本ハム","startDate":"2026-09-27T18:00:00.000+09:00","venue":"ZOZOマリンスタジアム（千葉マリンスタジアム）","region":"千葉県","url":"https://ticketjam.jp/tickets/marines/event/1040823","path":"/tickets/marines/event/1040823","listingCount":1,"teams":["marines","fighters"]},{"id":"1040824","team":"marines","name":"ロッテ vs 日本ハム","startDate":"2026-09-28T18:00:00.000+09:00","venue":"ZOZOマリンスタジアム（千葉マリンスタジアム）","region":"千葉県","url":"https://ticketjam.jp/tickets/marines/event/1040824","path":"/tickets/marines/event/1040824","listingCount":1,"teams":["marines","fighters"]},{"id":"1040761","team":"marines","name":"ソフトバンク vs ロッテ","startDate":"2026-08-11T14:00:00.000+09:00","venue":"みずほPayPayドーム福岡","region":"福岡県","url":"https://ticketjam.jp/tickets/softbankhawks/event/1040761","path":"/tickets/marines/event/1040761","listingCount":41,"teams":["marines","softbankhawks"]},{"id":"1040762","team":"marines","name":"ソフトバンク vs ロッテ","startDate":"2026-08-12T18:00:00.000+09:00","venue":"みずほPayPayドーム福岡","region":"福岡県","url":"https://ticketjam.jp/tickets/softbankhawks/event/1040762","path":"/tickets/marines/event/1040762","listingCount":56,"teams":["marines","softbankhawks"]},{"id":"1040763","team":"marines","name":"ソフトバンク vs ロッテ","startDate":"2026-08-13T18:00:00.000+09:00","venue":"みずほPayPayドーム福岡","region":"福岡県","url":"https://ticketjam.jp/tickets/softbankhawks/event/1040763","path":"/tickets/marines/event/1040763","listingCount":66,"teams":["marines","softbankhawks"]},{"id":"1040440","team":"marines","name":"ロッテ vs ソフトバンク","startDate":"2026-08-25T18:00:00.000+09:00","venue":"ZOZOマリンスタジアム（千葉マリンスタジアム）","region":"千葉県","url":"https://ticketjam.jp/tickets/marines/event/1040440","path":"/tickets/marines/event/1040440","listingCount":17,"teams":["marines","softbankhawks"]},{"id":"1040441","team":"marines","name":"ロッテ vs ソフトバンク","startDate":"2026-08-26T18:00:00.000+09:00","venue":"ZOZOマリンスタジアム（千葉マリンスタジアム）","region":"千葉県","url":"https://ticketjam.jp/tickets/marines/event/1040441","path":"/tickets/marines/event/1040441","listingCount":27,"teams":["marines","softbankhawks"]},{"id":"1040442","team":"marines","name":"ロッテ vs ソフトバンク","startDate":"2026-08-27T18:00:00.000+09:00","venue":"ZOZOマリンスタジアム（千葉マリンスタジアム）","region":"千葉県","url":"https://ticketjam.jp/tickets/marines/event/1040442","path":"/tickets/marines/event/1040442","listingCount":12,"teams":["marines","softbankhawks"]},{"id":"1190797","team":"marines","name":"ソフトバンク vs ロッテ","startDate":"2026-09-11T18:00:00.000+09:00","venue":"みずほPayPayドーム福岡","region":"福岡県","url":"https://ticketjam.jp/tickets/softbankhawks/event/1190797","path":"/tickets/marines/event/1190797","listingCount":25,"teams":["marines","softbankhawks"]},{"id":"1040764","team":"marines","name":"ソフトバンク vs ロッテ","startDate":"2026-09-12T14:00:00.000+09:00","venue":"みずほPayPayドーム福岡","region":"福岡県","url":"https://ticketjam.jp/tickets/softbankhawks/event/1040764","path":"/tickets/marines/event/1040764","listingCount":22,"teams":["marines","softbankhawks"]},{"id":"1040765","team":"marines","name":"ソフトバンク vs ロッテ","startDate":"2026-09-13T13:30:00.000+09:00","venue":"みずほPayPayドーム福岡","region":"福岡県","url":"https://ticketjam.jp/tickets/softbankhawks/event/1040765","path":"/tickets/marines/event/1040765","listingCount":34,"teams":["marines","softbankhawks"]},{"id":"1040529","team":"marines","name":"ロッテ vs 楽天","startDate":"2026-07-22T18:00:00.000+09:00","venue":"ZOZOマリンスタジアム（千葉マリンスタジアム）","region":"千葉県","url":"https://ticketjam.jp/tickets/marines/event/1040529","path":"/tickets/marines/event/1040529","listingCount":69,"teams":["marines","rakuteneagles"]},{"id":"1040530","team":"marines","name":"ロッテ vs 楽天","startDate":"2026-07-23T18:00:00.000+09:00","venue":"ZOZOマリンスタジアム（千葉マリンスタジアム）","region":"千葉県","url":"https://ticketjam.jp/tickets/marines/event/1040530","path":"/tickets/marines/event/1040530","listingCount":50,"teams":["marines","rakuteneagles"]},{"id":"1040806","team":"marines","name":"楽天 vs ロッテ","startDate":"2026-08-18T18:00:00.000+09:00","venue":"楽天モバイル 最強パーク宮城","region":"宮城県","url":"https://ticketjam.jp/tickets/rakuteneagles/event/1040806","path":"/tickets/marines/event/1040806","listingCount":22,"teams":["marines","rakuteneagles"]},{"id":"1040807","team":"marines","name":"楽天 vs ロッテ","startDate":"2026-08-19T18:00:00.000+09:00","venue":"楽天モバイル 最強パーク宮城","region":"宮城県","url":"https://ticketjam.jp/tickets/rakuteneagles/event/1040807","path":"/tickets/marines/event/1040807","listingCount":18,"teams":["marines","rakuteneagles"]},{"id":"1040808","team":"marines","name":"楽天 vs ロッテ","startDate":"2026-08-20T18:00:00.000+09:00","venue":"楽天モバイル 最強パーク宮城","region":"宮城県","url":"https://ticketjam.jp/tickets/rakuteneagles/event/1040808","path":"/tickets/marines/event/1040808","listingCount":23,"teams":["marines","rakuteneagles"]},{"id":"1040531","team":"marines","name":"ロッテ vs 楽天","startDate":"2026-09-08T18:00:00.000+09:00","venue":"ZOZOマリンスタジアム（千葉マリンスタジアム）","region":"千葉県","url":"https://ticketjam.jp/tickets/marines/event/1040531","path":"/tickets/marines/event/1040531","listingCount":5,"teams":["marines","rakuteneagles"]},{"id":"1040532","team":"marines","name":"ロッテ vs 楽天","startDate":"2026-09-09T18:00:00.000+09:00","venue":"ZOZOマリンスタジアム（千葉マリンスタジアム）","region":"千葉県","url":"https://ticketjam.jp/tickets/marines/event/1040532","path":"/tickets/marines/event/1040532","listingCount":16,"teams":["marines","rakuteneagles"]},{"id":"1040533","team":"marines","name":"ロッテ vs 楽天","startDate":"2026-09-10T18:00:00.000+09:00","venue":"ZOZOマリンスタジアム（千葉マリンスタジアム）","region":"千葉県","url":"https://ticketjam.jp/tickets/marines/event/1040533","path":"/tickets/marines/event/1040533","listingCount":12,"teams":["marines","rakuteneagles"]},{"id":"1040534","team":"marines","name":"ロッテ vs 楽天","startDate":"2026-09-16T18:00:00.000+09:00","venue":"ZOZOマリンスタジアム（千葉マリンスタジアム）","region":"千葉県","url":"https://ticketjam.jp/tickets/marines/event/1040534","path":"/tickets/marines/event/1040534","listingCount":7,"teams":["marines","rakuteneagles"]},{"id":"1040535","team":"marines","name":"ロッテ vs 楽天","startDate":"2026-09-17T18:00:00.000+09:00","venue":"ZOZOマリンスタジアム（千葉マリンスタジアム）","region":"千葉県","url":"https://ticketjam.jp/tickets/marines/event/1040535","path":"/tickets/marines/event/1040535","listingCount":7,"teams":["marines","rakuteneagles"]},{"id":"1040809","team":"marines","name":"楽天 vs ロッテ","startDate":"2026-09-29T18:00:00.000+09:00","venue":"楽天モバイル 最強パーク宮城","region":"宮城県","url":"https://ticketjam.jp/tickets/rakuteneagles/event/1040809","path":"/tickets/marines/event/1040809","listingCount":null,"teams":["marines","rakuteneagles"]},{"id":"1040810","team":"marines","name":"楽天 vs ロッテ","startDate":"2026-09-30T18:00:00.000+09:00","venue":"楽天モバイル 最強パーク宮城","region":"宮城県","url":"https://ticketjam.jp/tickets/rakuteneagles/event/1040810","path":"/tickets/marines/event/1040810","listingCount":1,"teams":["marines","rakuteneagles"]},{"id":"1040688","team":"marines","name":"ロッテ vs 西武","startDate":"2026-08-04T18:00:00.000+09:00","venue":"ZOZOマリンスタジアム（千葉マリンスタジアム）","region":"千葉県","url":"https://ticketjam.jp/tickets/marines/event/1040688","path":"/tickets/marines/event/1040688","listingCount":31,"teams":["marines","seibulions"]},{"id":"1040689","team":"marines","name":"ロッテ vs 西武","startDate":"2026-08-05T18:00:00.000+09:00","venue":"ZOZOマリンスタジアム（千葉マリンスタジアム）","region":"千葉県","url":"https://ticketjam.jp/tickets/marines/event/1040689","path":"/tickets/marines/event/1040689","listingCount":47,"teams":["marines","seibulions"]},{"id":"1040384","team":"marines","name":"西武 vs ロッテ","startDate":"2026-08-14T18:00:00.000+09:00","venue":"ベルーナドーム","region":"埼玉県","url":"https://ticketjam.jp/tickets/seibulions/event/1040384","path":"/tickets/marines/event/1040384","listingCount":46,"teams":["marines","seibulions"]},{"id":"1040385","team":"marines","name":"西武 vs ロッテ","startDate":"2026-08-15T17:00:00.000+09:00","venue":"ベルーナドーム","region":"埼玉県","url":"https://ticketjam.jp/tickets/seibulions/event/1040385","path":"/tickets/marines/event/1040385","listingCount":46,"teams":["marines","seibulions"]},{"id":"1040386","team":"marines","name":"西武 vs ロッテ","startDate":"2026-08-16T17:00:00.000+09:00","venue":"ベルーナドーム","region":"埼玉県","url":"https://ticketjam.jp/tickets/seibulions/event/1040386","path":"/tickets/marines/event/1040386","listingCount":56,"teams":["marines","seibulions"]},{"id":"1040690","team":"marines","name":"ロッテ vs 西武","startDate":"2026-09-01T18:00:00.000+09:00","venue":"ZOZOマリンスタジアム（千葉マリンスタジアム）","region":"千葉県","url":"https://ticketjam.jp/tickets/marines/event/1040690","path":"/tickets/marines/event/1040690","listingCount":18,"teams":["marines","seibulions"]},{"id":"1040691","team":"marines","name":"ロッテ vs 西武","startDate":"2026-09-19T18:00:00.000+09:00","venue":"ZOZOマリンスタジアム（千葉マリンスタジアム）","region":"千葉県","url":"https://ticketjam.jp/tickets/marines/event/1040691","path":"/tickets/marines/event/1040691","listingCount":2,"teams":["marines","seibulions"]},{"id":"1040692","team":"marines","name":"ロッテ vs 西武","startDate":"2026-09-20T18:00:00.000+09:00","venue":"ZOZOマリンスタジアム（千葉マリンスタジアム）","region":"千葉県","url":"https://ticketjam.jp/tickets/marines/event/1040692","path":"/tickets/marines/event/1040692","listingCount":1,"teams":["marines","seibulions"]},{"id":"1040693","team":"marines","name":"ロッテ vs 西武","startDate":"2026-09-21T18:00:00.000+09:00","venue":"ZOZOマリンスタジアム（千葉マリンスタジアム）","region":"千葉県","url":"https://ticketjam.jp/tickets/marines/event/1040693","path":"/tickets/marines/event/1040693","listingCount":1,"teams":["marines","seibulions"]},{"id":"1040387","team":"marines","name":"西武 vs ロッテ","startDate":"2026-09-25T18:00:00.000+09:00","venue":"ベルーナドーム","region":"埼玉県","url":"https://ticketjam.jp/tickets/seibulions/event/1040387","path":"/tickets/marines/event/1040387","listingCount":10,"teams":["marines","seibulions"]},{"id":"1040388","team":"marines","name":"西武 vs ロッテ","startDate":"2026-09-26T14:00:00.000+09:00","venue":"ベルーナドーム","region":"埼玉県","url":"https://ticketjam.jp/tickets/seibulions/event/1040388","path":"/tickets/marines/event/1040388","listingCount":15,"teams":["marines","seibulions"]},{"id":"1040571","team":"marines","name":"オリックス vs ロッテ","startDate":"2026-07-24T18:00:00.000+09:00","venue":"京セラドーム大阪","region":"大阪府","url":"https://ticketjam.jp/tickets/buffaloes/event/1040571","path":"/tickets/marines/event/1040571","listingCount":53,"teams":["marines","buffaloes"]},{"id":"1040572","team":"marines","name":"オリックス vs ロッテ","startDate":"2026-07-25T14:00:00.000+09:00","venue":"京セラドーム大阪","region":"大阪府","url":"https://ticketjam.jp/tickets/buffaloes/event/1040572","path":"/tickets/marines/event/1040572","listingCount":94,"teams":["marines","buffaloes"]},{"id":"1040573","team":"marines","name":"オリックス vs ロッテ","startDate":"2026-07-26T13:00:00.000+09:00","venue":"京セラドーム大阪","region":"大阪府","url":"https://ticketjam.jp/tickets/buffaloes/event/1040573","path":"/tickets/marines/event/1040573","listingCount":66,"teams":["marines","buffaloes"]},{"id":"1040738","team":"marines","name":"ロッテ vs オリックス","startDate":"2026-08-07T18:00:00.000+09:00","venue":"ZOZOマリンスタジアム（千葉マリンスタジアム）","region":"千葉県","url":"https://ticketjam.jp/tickets/marines/event/1040738","path":"/tickets/marines/event/1040738","listingCount":53,"teams":["marines","buffaloes"]},{"id":"1040739","team":"marines","name":"ロッテ vs オリックス","startDate":"2026-08-08T18:00:00.000+09:00","venue":"ZOZOマリンスタジアム（千葉マリンスタジアム）","region":"千葉県","url":"https://ticketjam.jp/tickets/marines/event/1040739","path":"/tickets/marines/event/1040739","listingCount":62,"teams":["marines","buffaloes"]},{"id":"1040740","team":"marines","name":"ロッテ vs オリックス","startDate":"2026-08-09T17:00:00.000+09:00","venue":"ZOZOマリンスタジアム（千葉マリンスタジアム）","region":"千葉県","url":"https://ticketjam.jp/tickets/marines/event/1040740","path":"/tickets/marines/event/1040740","listingCount":28,"teams":["marines","buffaloes"]},{"id":"1040574","team":"marines","name":"オリックス vs ロッテ","startDate":"2026-09-04T18:00:00.000+09:00","venue":"京セラドーム大阪","region":"大阪府","url":"https://ticketjam.jp/tickets/buffaloes/event/1040574","path":"/tickets/marines/event/1040574","listingCount":15,"teams":["marines","buffaloes"]},{"id":"1040575","team":"marines","name":"オリックス vs ロッテ","startDate":"2026-09-05T14:00:00.000+09:00","venue":"京セラドーム大阪","region":"大阪府","url":"https://ticketjam.jp/tickets/buffaloes/event/1040575","path":"/tickets/marines/event/1040575","listingCount":25,"teams":["marines","buffaloes"]},{"id":"1040576","team":"marines","name":"オリックス vs ロッテ","startDate":"2026-09-06T13:00:00.000+09:00","venue":"京セラドーム大阪","region":"大阪府","url":"https://ticketjam.jp/tickets/buffaloes/event/1040576","path":"/tickets/marines/event/1040576","listingCount":19,"teams":["marines","buffaloes"]},{"id":"1162398","team":"marines","name":"ロッテ vs オリックス","startDate":"2026-09-22T18:00:00.000+09:00","venue":"ZOZOマリンスタジアム（千葉マリンスタジアム）","region":"千葉県","url":"https://ticketjam.jp/tickets/marines/event/1162398","path":"/tickets/marines/event/1162398","listingCount":1,"teams":["marines","buffaloes"]},{"id":"1040741","team":"marines","name":"ロッテ vs オリックス","startDate":"2026-09-23T17:00:00.000+09:00","venue":"ZOZOマリンスタジアム（千葉マリンスタジアム）","region":"千葉県","url":"https://ticketjam.jp/tickets/marines/event/1040741","path":"/tickets/marines/event/1040741","listingCount":1,"teams":["marines","buffaloes"]},{"id":"1040523","team":"seibulions","name":"西武 vs 日本ハム","startDate":"2026-07-22T18:00:00.000+09:00","venue":"ベルーナドーム","region":"埼玉県","url":"https://ticketjam.jp/tickets/seibulions/event/1040523","path":"/tickets/seibulions/event/1040523","listingCount":50,"teams":["seibulions","fighters"]},{"id":"1040524","team":"seibulions","name":"西武 vs 日本ハム","startDate":"2026-07-23T18:00:00.000+09:00","venue":"ベルーナドーム","region":"埼玉県","url":"https://ticketjam.jp/tickets/seibulions/event/1040524","path":"/tickets/seibulions/event/1040524","listingCount":87,"teams":["seibulions","fighters"]},{"id":"1040755","team":"seibulions","name":"日本ハム vs 西武","startDate":"2026-08-11T14:00:00.000+09:00","venue":"エスコンフィールド北海道","region":"北海道","url":"https://ticketjam.jp/tickets/fighters/event/1040755","path":"/tickets/seibulions/event/1040755","listingCount":37,"teams":["seibulions","fighters"]},{"id":"1040756","team":"seibulions","name":"日本ハム vs 西武","startDate":"2026-08-12T18:00:00.000+09:00","venue":"エスコンフィールド北海道","region":"北海道","url":"https://ticketjam.jp/tickets/fighters/event/1040756","path":"/tickets/seibulions/event/1040756","listingCount":22,"teams":["seibulions","fighters"]},{"id":"1040757","team":"seibulions","name":"日本ハム vs 西武","startDate":"2026-08-13T18:00:00.000+09:00","venue":"エスコンフィールド北海道","region":"北海道","url":"https://ticketjam.jp/tickets/fighters/event/1040757","path":"/tickets/seibulions/event/1040757","listingCount":34,"teams":["seibulions","fighters"]},{"id":"1040525","team":"seibulions","name":"西武 vs 日本ハム","startDate":"2026-08-25T18:00:00.000+09:00","venue":"ベルーナドーム","region":"埼玉県","url":"https://ticketjam.jp/tickets/seibulions/event/1040525","path":"/tickets/seibulions/event/1040525","listingCount":46,"teams":["seibulions","fighters"]},{"id":"1040526","team":"seibulions","name":"西武 vs 日本ハム","startDate":"2026-08-26T18:00:00.000+09:00","venue":"ベルーナドーム","region":"埼玉県","url":"https://ticketjam.jp/tickets/seibulions/event/1040526","path":"/tickets/seibulions/event/1040526","listingCount":35,"teams":["seibulions","fighters"]},{"id":"1040527","team":"seibulions","name":"西武 vs 日本ハム","startDate":"2026-09-12T18:00:00.000+09:00","venue":"ベルーナドーム","region":"埼玉県","url":"https://ticketjam.jp/tickets/seibulions/event/1040527","path":"/tickets/seibulions/event/1040527","listingCount":35,"teams":["seibulions","fighters"]},{"id":"1040528","team":"seibulions","name":"西武 vs 日本ハム","startDate":"2026-09-13T17:00:00.000+09:00","venue":"ベルーナドーム","region":"埼玉県","url":"https://ticketjam.jp/tickets/seibulions/event/1040528","path":"/tickets/seibulions/event/1040528","listingCount":29,"teams":["seibulions","fighters"]},{"id":"1040758","team":"seibulions","name":"日本ハム vs 西武","startDate":"2026-09-17T18:00:00.000+09:00","venue":"エスコンフィールド北海道","region":"北海道","url":"https://ticketjam.jp/tickets/fighters/event/1040758","path":"/tickets/seibulions/event/1040758","listingCount":29,"teams":["seibulions","fighters"]},{"id":"1040565","team":"seibulions","name":"西武 vs ソフトバンク","startDate":"2026-07-24T18:00:00.000+09:00","venue":"ベルーナドーム","region":"埼玉県","url":"https://ticketjam.jp/tickets/seibulions/event/1040565","path":"/tickets/seibulions/event/1040565","listingCount":82,"teams":["seibulions","softbankhawks"]},{"id":"1040566","team":"seibulions","name":"西武 vs ソフトバンク","startDate":"2026-07-25T18:00:00.000+09:00","venue":"ベルーナドーム","region":"埼玉県","url":"https://ticketjam.jp/tickets/seibulions/event/1040566","path":"/tickets/seibulions/event/1040566","listingCount":216,"teams":["seibulions","softbankhawks"]},{"id":"1040567","team":"seibulions","name":"西武 vs ソフトバンク","startDate":"2026-07-26T17:00:00.000+09:00","venue":"ベルーナドーム","region":"埼玉県","url":"https://ticketjam.jp/tickets/seibulions/event/1040567","path":"/tickets/seibulions/event/1040567","listingCount":121,"teams":["seibulions","softbankhawks"]},{"id":"1040568","team":"seibulions","name":"西武 vs ソフトバンク","startDate":"2026-08-07T18:00:00.000+09:00","venue":"ベルーナドーム","region":"埼玉県","url":"https://ticketjam.jp/tickets/seibulions/event/1040568","path":"/tickets/seibulions/event/1040568","listingCount":83,"teams":["seibulions","softbankhawks"]},{"id":"1040570","team":"seibulions","name":"西武 vs ソフトバンク","startDate":"2026-08-08T18:00:00.000+09:00","venue":"ベルーナドーム","region":"埼玉県","url":"https://ticketjam.jp/tickets/seibulions/event/1040570","path":"/tickets/seibulions/event/1040570","listingCount":118,"teams":["seibulions","softbankhawks"]},{"id":"1040569","team":"seibulions","name":"西武 vs ソフトバンク","startDate":"2026-08-09T17:00:00.000+09:00","venue":"ベルーナドーム","region":"埼玉県","url":"https://ticketjam.jp/tickets/seibulions/event/1040569","path":"/tickets/seibulions/event/1040569","listingCount":76,"teams":["seibulions","softbankhawks"]},{"id":"1040732","team":"seibulions","name":"ソフトバンク vs 西武","startDate":"2026-09-04T18:00:00.000+09:00","venue":"みずほPayPayドーム福岡","region":"福岡県","url":"https://ticketjam.jp/tickets/softbankhawks/event/1040732","path":"/tickets/seibulions/event/1040732","listingCount":32,"teams":["seibulions","softbankhawks"]},{"id":"1040733","team":"seibulions","name":"ソフトバンク vs 西武","startDate":"2026-09-05T14:00:00.000+09:00","venue":"みずほPayPayドーム福岡","region":"福岡県","url":"https://ticketjam.jp/tickets/softbankhawks/event/1040733","path":"/tickets/seibulions/event/1040733","listingCount":24,"teams":["seibulions","softbankhawks"]},{"id":"1040734","team":"seibulions","name":"ソフトバンク vs 西武","startDate":"2026-09-06T13:00:00.000+09:00","venue":"みずほPayPayドーム福岡","region":"福岡県","url":"https://ticketjam.jp/tickets/softbankhawks/event/1040734","path":"/tickets/seibulions/event/1040734","listingCount":28,"teams":["seibulions","softbankhawks"]},{"id":"1040735","team":"seibulions","name":"ソフトバンク vs 西武","startDate":"2026-09-22T18:00:00.000+09:00","venue":"みずほPayPayドーム福岡","region":"福岡県","url":"https://ticketjam.jp/tickets/softbankhawks/event/1040735","path":"/tickets/seibulions/event/1040735","listingCount":20,"teams":["seibulions","softbankhawks"]},{"id":"1040736","team":"seibulions","name":"ソフトバンク vs 西武","startDate":"2026-09-23T14:00:00.000+09:00","venue":"みずほPayPayドーム福岡","region":"福岡県","url":"https://ticketjam.jp/tickets/softbankhawks/event/1040736","path":"/tickets/seibulions/event/1040736","listingCount":21,"teams":["seibulions","softbankhawks"]},{"id":"1040430","team":"seibulions","name":"楽天 vs 西武","startDate":"2026-08-21T18:00:00.000+09:00","venue":"楽天モバイル 最強パーク宮城","region":"宮城県","url":"https://ticketjam.jp/tickets/rakuteneagles/event/1040430","path":"/tickets/seibulions/event/1040430","listingCount":29,"teams":["seibulions","rakuteneagles"]},{"id":"1040431","team":"seibulions","name":"楽天 vs 西武","startDate":"2026-08-22T18:00:00.000+09:00","venue":"楽天モバイル 最強パーク宮城","region":"宮城県","url":"https://ticketjam.jp/tickets/rakuteneagles/event/1040431","path":"/tickets/seibulions/event/1040431","listingCount":28,"teams":["seibulions","rakuteneagles"]},{"id":"1040432","team":"seibulions","name":"楽天 vs 西武","startDate":"2026-08-23T16:00:00.000+09:00","venue":"楽天モバイル 最強パーク宮城","region":"宮城県","url":"https://ticketjam.jp/tickets/rakuteneagles/event/1040432","path":"/tickets/seibulions/event/1040432","listingCount":31,"teams":["seibulions","rakuteneagles"]},{"id":"1040828","team":"seibulions","name":"西武 vs 楽天","startDate":"2026-08-28T18:00:00.000+09:00","venue":"ベルーナドーム","region":"埼玉県","url":"https://ticketjam.jp/tickets/seibulions/event/1040828","path":"/tickets/seibulions/event/1040828","listingCount":25,"teams":["seibulions","rakuteneagles"]},{"id":"1040829","team":"seibulions","name":"西武 vs 楽天","startDate":"2026-08-29T17:00:00.000+09:00","venue":"ベルーナドーム","region":"埼玉県","url":"https://ticketjam.jp/tickets/seibulions/event/1040829","path":"/tickets/seibulions/event/1040829","listingCount":80,"teams":["seibulions","rakuteneagles"]},{"id":"1040830","team":"seibulions","name":"西武 vs 楽天","startDate":"2026-08-30T17:00:00.000+09:00","venue":"ベルーナドーム","region":"埼玉県","url":"https://ticketjam.jp/tickets/seibulions/event/1040830","path":"/tickets/seibulions/event/1040830","listingCount":46,"teams":["seibulions","rakuteneagles"]},{"id":"1040433","team":"seibulions","name":"楽天 vs 西武","startDate":"2026-09-15T18:00:00.000+09:00","venue":"楽天モバイル 最強パーク宮城","region":"宮城県","url":"https://ticketjam.jp/tickets/rakuteneagles/event/1040433","path":"/tickets/seibulions/event/1040433","listingCount":1,"teams":["seibulions","rakuteneagles"]},{"id":"1040831","team":"seibulions","name":"西武 vs 楽天","startDate":"2026-09-27T18:00:00.000+09:00","venue":"ベルーナドーム","region":"埼玉県","url":"https://ticketjam.jp/tickets/seibulions/event/1040831","path":"/tickets/seibulions/event/1040831","listingCount":9,"teams":["seibulions","rakuteneagles"]},{"id":"1040832","team":"seibulions","name":"西武 vs 楽天","startDate":"2026-09-28T18:00:00.000+09:00","venue":"ベルーナドーム","region":"埼玉県","url":"https://ticketjam.jp/tickets/seibulions/event/1040832","path":"/tickets/seibulions/event/1040832","listingCount":12,"teams":["seibulions","rakuteneagles"]},{"id":"1040627","team":"seibulions","name":"西武 vs オリックス","startDate":"2026-07-31T18:00:00.000+09:00","venue":"ベルーナドーム","region":"埼玉県","url":"https://ticketjam.jp/tickets/seibulions/event/1040627","path":"/tickets/seibulions/event/1040627","listingCount":62,"teams":["seibulions","buffaloes"]},{"id":"1040628","team":"seibulions","name":"西武 vs オリックス","startDate":"2026-08-01T17:00:00.000+09:00","venue":"ベルーナドーム","region":"埼玉県","url":"https://ticketjam.jp/tickets/seibulions/event/1040628","path":"/tickets/seibulions/event/1040628","listingCount":168,"teams":["seibulions","buffaloes"]},{"id":"1040629","team":"seibulions","name":"西武 vs オリックス","startDate":"2026-08-02T17:00:00.000+09:00","venue":"ベルーナドーム","region":"埼玉県","url":"https://ticketjam.jp/tickets/seibulions/event/1040629","path":"/tickets/seibulions/event/1040629","listingCount":90,"teams":["seibulions","buffaloes"]},{"id":"1040630","team":"seibulions","name":"西武 vs オリックス","startDate":"2026-08-18T18:00:00.000+09:00","venue":"東京ドーム","region":"東京都","url":"https://ticketjam.jp/tickets/seibulions/event/1040630","path":"/tickets/seibulions/event/1040630","listingCount":82,"teams":["seibulions","buffaloes"]},{"id":"1040631","team":"seibulions","name":"西武 vs オリックス","startDate":"2026-08-19T18:00:00.000+09:00","venue":"ベルーナドーム","region":"埼玉県","url":"https://ticketjam.jp/tickets/seibulions/event/1040631","path":"/tickets/seibulions/event/1040631","listingCount":45,"teams":["seibulions","buffaloes"]},{"id":"1040632","team":"seibulions","name":"西武 vs オリックス","startDate":"2026-08-20T18:00:00.000+09:00","venue":"ベルーナドーム","region":"埼玉県","url":"https://ticketjam.jp/tickets/seibulions/event/1040632","path":"/tickets/seibulions/event/1040632","listingCount":54,"teams":["seibulions","buffaloes"]},{"id":"1040635","team":"seibulions","name":"オリックス vs 西武","startDate":"2026-09-08T18:00:00.000+09:00","venue":"京セラドーム大阪","region":"大阪府","url":"https://ticketjam.jp/tickets/buffaloes/event/1040635","path":"/tickets/seibulions/event/1040635","listingCount":11,"teams":["seibulions","buffaloes"]},{"id":"1040636","team":"seibulions","name":"オリックス vs 西武","startDate":"2026-09-09T18:00:00.000+09:00","venue":"ほっともっとフィールド神戸（神戸総合運動公園野球場）","region":"兵庫県","url":"https://ticketjam.jp/tickets/buffaloes/event/1040636","path":"/tickets/seibulions/event/1040636","listingCount":9,"teams":["seibulions","buffaloes"]},{"id":"1040637","team":"seibulions","name":"オリックス vs 西武","startDate":"2026-09-10T18:00:00.000+09:00","venue":"ほっともっとフィールド神戸（神戸総合運動公園野球場）","region":"兵庫県","url":"https://ticketjam.jp/tickets/buffaloes/event/1040637","path":"/tickets/seibulions/event/1040637","listingCount":7,"teams":["seibulions","buffaloes"]},{"id":"1233787","team":"seibulions","name":"オリックス vs 西武","startDate":"2026-09-11T18:00:00.000+09:00","venue":"京セラドーム大阪","region":"大阪府","url":"https://ticketjam.jp/tickets/buffaloes/event/1233787","path":"/tickets/seibulions/event/1233787","listingCount":null,"teams":["seibulions","buffaloes"]},{"id":"1040633","team":"seibulions","name":"西武 vs オリックス","startDate":"2026-09-29T18:00:00.000+09:00","venue":"ベルーナドーム","region":"埼玉県","url":"https://ticketjam.jp/tickets/seibulions/event/1040633","path":"/tickets/seibulions/event/1040633","listingCount":17,"teams":["seibulions","buffaloes"]},{"id":"1040721","team":"hanshintigers","name":"阪神 vs 中日","startDate":"2026-08-07T18:00:00.000+09:00","venue":"京セラドーム大阪","region":"大阪府","url":"https://ticketjam.jp/tickets/hanshintigers/event/1040721","path":"/tickets/hanshintigers/event/1040721","listingCount":139,"teams":["hanshintigers","dragons"]},{"id":"1040722","team":"hanshintigers","name":"阪神 vs 中日","startDate":"2026-08-08T18:00:00.000+09:00","venue":"京セラドーム大阪","region":"大阪府","url":"https://ticketjam.jp/tickets/hanshintigers/event/1040722","path":"/tickets/hanshintigers/event/1040722","listingCount":96,"teams":["hanshintigers","dragons"]},{"id":"1040723","team":"hanshintigers","name":"阪神 vs 中日","startDate":"2026-08-09T18:00:00.000+09:00","venue":"京セラドーム大阪","region":"大阪府","url":"https://ticketjam.jp/tickets/hanshintigers/event/1040723","path":"/tickets/hanshintigers/event/1040723","listingCount":158,"teams":["hanshintigers","dragons"]},{"id":"1040346","team":"hanshintigers","name":"中日 vs 阪神","startDate":"2026-08-25T18:00:00.000+09:00","venue":"バンテリンドーム ナゴヤ","region":"愛知県","url":"https://ticketjam.jp/tickets/dragons/event/1040346","path":"/tickets/hanshintigers/event/1040346","listingCount":129,"teams":["hanshintigers","dragons"]},{"id":"1040347","team":"hanshintigers","name":"中日 vs 阪神","startDate":"2026-08-26T18:00:00.000+09:00","venue":"バンテリンドーム ナゴヤ","region":"愛知県","url":"https://ticketjam.jp/tickets/dragons/event/1040347","path":"/tickets/hanshintigers/event/1040347","listingCount":147,"teams":["hanshintigers","dragons"]},{"id":"1040348","team":"hanshintigers","name":"中日 vs 阪神","startDate":"2026-08-27T18:00:00.000+09:00","venue":"バンテリンドーム ナゴヤ","region":"愛知県","url":"https://ticketjam.jp/tickets/dragons/event/1040348","path":"/tickets/hanshintigers/event/1040348","listingCount":135,"teams":["hanshintigers","dragons"]},{"id":"1040724","team":"hanshintigers","name":"阪神 vs 中日","startDate":"2026-09-13T18:00:00.000+09:00","venue":"阪神甲子園球場","region":"兵庫県","url":"https://ticketjam.jp/tickets/hanshintigers/event/1040724","path":"/tickets/hanshintigers/event/1040724","listingCount":48,"teams":["hanshintigers","dragons"]},{"id":"1190989","team":"hanshintigers","name":"阪神 vs 中日","startDate":"2026-09-14T18:00:00.000+09:00","venue":"阪神甲子園球場","region":"兵庫県","url":"https://ticketjam.jp/tickets/hanshintigers/event/1190989","path":"/tickets/hanshintigers/event/1190989","listingCount":80,"teams":["hanshintigers","dragons"]},{"id":"1040417","team":"hanshintigers","name":"広島 vs 阪神","startDate":"2026-08-14T18:00:00.000+09:00","venue":"MAZDA Zoom-Zoom スタジアム 広島","region":"広島県","url":"https://ticketjam.jp/tickets/carp/event/1040417","path":"/tickets/hanshintigers/event/1040417","listingCount":39,"teams":["hanshintigers","carp"]},{"id":"1040418","team":"hanshintigers","name":"広島 vs 阪神","startDate":"2026-08-15T18:00:00.000+09:00","venue":"MAZDA Zoom-Zoom スタジアム 広島","region":"広島県","url":"https://ticketjam.jp/tickets/carp/event/1040418","path":"/tickets/hanshintigers/event/1040418","listingCount":138,"teams":["hanshintigers","carp"]},{"id":"1040419","team":"hanshintigers","name":"広島 vs 阪神","startDate":"2026-08-16T18:00:00.000+09:00","venue":"MAZDA Zoom-Zoom スタジアム 広島","region":"広島県","url":"https://ticketjam.jp/tickets/carp/event/1040419","path":"/tickets/hanshintigers/event/1040419","listingCount":170,"teams":["hanshintigers","carp"]},{"id":"1040778","team":"hanshintigers","name":"阪神 vs 広島","startDate":"2026-09-08T18:00:00.000+09:00","venue":"阪神甲子園球場","region":"兵庫県","url":"https://ticketjam.jp/tickets/hanshintigers/event/1040778","path":"/tickets/hanshintigers/event/1040778","listingCount":76,"teams":["hanshintigers","carp"]},{"id":"1040779","team":"hanshintigers","name":"阪神 vs 広島","startDate":"2026-09-09T18:00:00.000+09:00","venue":"阪神甲子園球場","region":"兵庫県","url":"https://ticketjam.jp/tickets/hanshintigers/event/1040779","path":"/tickets/hanshintigers/event/1040779","listingCount":74,"teams":["hanshintigers","carp"]},{"id":"1040780","team":"hanshintigers","name":"阪神 vs 広島","startDate":"2026-09-10T18:00:00.000+09:00","venue":"阪神甲子園球場","region":"兵庫県","url":"https://ticketjam.jp/tickets/hanshintigers/event/1040780","path":"/tickets/hanshintigers/event/1040780","listingCount":64,"teams":["hanshintigers","carp"]},{"id":"1040781","team":"hanshintigers","name":"阪神 vs 広島","startDate":"2026-09-18T18:00:00.000+09:00","venue":"阪神甲子園球場","region":"兵庫県","url":"https://ticketjam.jp/tickets/hanshintigers/event/1040781","path":"/tickets/hanshintigers/event/1040781","listingCount":37,"teams":["hanshintigers","carp"]},{"id":"1040782","team":"hanshintigers","name":"阪神 vs 広島","startDate":"2026-09-19T18:00:00.000+09:00","venue":"阪神甲子園球場","region":"兵庫県","url":"https://ticketjam.jp/tickets/hanshintigers/event/1040782","path":"/tickets/hanshintigers/event/1040782","listingCount":30,"teams":["hanshintigers","carp"]},{"id":"1040600","team":"dragons","name":"広島 vs 中日","startDate":"2026-07-31T18:00:00.000+09:00","venue":"MAZDA Zoom-Zoom スタジアム 広島","region":"広島県","url":"https://ticketjam.jp/tickets/carp/event/1040600","path":"/tickets/dragons/event/1040600","listingCount":44,"teams":["dragons","carp"]},{"id":"1040601","team":"dragons","name":"広島 vs 中日","startDate":"2026-08-01T18:00:00.000+09:00","venue":"MAZDA Zoom-Zoom スタジアム 広島","region":"広島県","url":"https://ticketjam.jp/tickets/carp/event/1040601","path":"/tickets/dragons/event/1040601","listingCount":67,"teams":["dragons","carp"]},{"id":"1040602","team":"dragons","name":"広島 vs 中日","startDate":"2026-08-02T18:00:00.000+09:00","venue":"MAZDA Zoom-Zoom スタジアム 広島","region":"広島県","url":"https://ticketjam.jp/tickets/carp/event/1040602","path":"/tickets/dragons/event/1040602","listingCount":94,"teams":["dragons","carp"]},{"id":"1040603","team":"dragons","name":"広島 vs 中日","startDate":"2026-08-18T18:00:00.000+09:00","venue":"MAZDA Zoom-Zoom スタジアム 広島","region":"広島県","url":"https://ticketjam.jp/tickets/carp/event/1040603","path":"/tickets/dragons/event/1040603","listingCount":29,"teams":["dragons","carp"]},{"id":"1040604","team":"dragons","name":"広島 vs 中日","startDate":"2026-08-19T18:00:00.000+09:00","venue":"MAZDA Zoom-Zoom スタジアム 広島","region":"広島県","url":"https://ticketjam.jp/tickets/carp/event/1040604","path":"/tickets/dragons/event/1040604","listingCount":52,"teams":["dragons","carp"]},{"id":"1040605","team":"dragons","name":"広島 vs 中日","startDate":"2026-08-20T18:00:00.000+09:00","venue":"MAZDA Zoom-Zoom スタジアム 広島","region":"広島県","url":"https://ticketjam.jp/tickets/carp/event/1040605","path":"/tickets/dragons/event/1040605","listingCount":46,"teams":["dragons","carp"]},{"id":"1040800","team":"dragons","name":"中日 vs 広島","startDate":"2026-09-01T18:00:00.000+09:00","venue":"バンテリンドーム ナゴヤ","region":"愛知県","url":"https://ticketjam.jp/tickets/dragons/event/1040800","path":"/tickets/dragons/event/1040800","listingCount":105,"teams":["dragons","carp"]},{"id":"1040801","team":"dragons","name":"中日 vs 広島","startDate":"2026-09-02T18:00:00.000+09:00","venue":"バンテリンドーム ナゴヤ","region":"愛知県","url":"https://ticketjam.jp/tickets/dragons/event/1040801","path":"/tickets/dragons/event/1040801","listingCount":97,"teams":["dragons","carp"]},{"id":"1040802","team":"dragons","name":"中日 vs 広島","startDate":"2026-09-03T18:00:00.000+09:00","venue":"バンテリンドーム ナゴヤ","region":"愛知県","url":"https://ticketjam.jp/tickets/dragons/event/1040802","path":"/tickets/dragons/event/1040802","listingCount":104,"teams":["dragons","carp"]},{"id":"1040803","team":"dragons","name":"中日 vs 広島","startDate":"2026-09-20T18:00:00.000+09:00","venue":"バンテリンドーム ナゴヤ","region":"愛知県","url":"https://ticketjam.jp/tickets/dragons/event/1040803","path":"/tickets/dragons/event/1040803","listingCount":78,"teams":["dragons","carp"]},{"id":"1040804","team":"dragons","name":"中日 vs 広島","startDate":"2026-09-21T14:00:00.000+09:00","venue":"バンテリンドーム ナゴヤ","region":"愛知県","url":"https://ticketjam.jp/tickets/dragons/event/1040804","path":"/tickets/dragons/event/1040804","listingCount":115,"teams":["dragons","carp"]},{"id":"1040701","team":"fighters","name":"ソフトバンク vs 日本ハム","startDate":"2026-08-04T18:00:00.000+09:00","venue":"京セラドーム大阪","region":"大阪府","url":"https://ticketjam.jp/tickets/softbankhawks/event/1040701","path":"/tickets/fighters/event/1040701","listingCount":41,"teams":["fighters","softbankhawks"]},{"id":"1040702","team":"fighters","name":"ソフトバンク vs 日本ハム","startDate":"2026-08-05T18:00:00.000+09:00","venue":"みずほPayPayドーム福岡","region":"福岡県","url":"https://ticketjam.jp/tickets/softbankhawks/event/1040702","path":"/tickets/fighters/event/1040702","listingCount":54,"teams":["fighters","softbankhawks"]},{"id":"1040703","team":"fighters","name":"ソフトバンク vs 日本ハム","startDate":"2026-08-06T18:00:00.000+09:00","venue":"みずほPayPayドーム福岡","region":"福岡県","url":"https://ticketjam.jp/tickets/softbankhawks/event/1040703","path":"/tickets/fighters/event/1040703","listingCount":41,"teams":["fighters","softbankhawks"]},{"id":"1040362","team":"fighters","name":"日本ハム vs ソフトバンク","startDate":"2026-08-18T14:00:00.000+09:00","venue":"エスコンフィールド北海道","region":"北海道","url":"https://ticketjam.jp/tickets/fighters/event/1040362","path":"/tickets/fighters/event/1040362","listingCount":29,"teams":["fighters","softbankhawks"]},{"id":"1040363","team":"fighters","name":"日本ハム vs ソフトバンク","startDate":"2026-08-19T14:00:00.000+09:00","venue":"エスコンフィールド北海道","region":"北海道","url":"https://ticketjam.jp/tickets/fighters/event/1040363","path":"/tickets/fighters/event/1040363","listingCount":18,"teams":["fighters","softbankhawks"]},{"id":"1040364","team":"fighters","name":"日本ハム vs ソフトバンク","startDate":"2026-08-20T14:00:00.000+09:00","venue":"エスコンフィールド北海道","region":"北海道","url":"https://ticketjam.jp/tickets/fighters/event/1040364","path":"/tickets/fighters/event/1040364","listingCount":25,"teams":["fighters","softbankhawks"]},{"id":"1040365","team":"fighters","name":"日本ハム vs ソフトバンク","startDate":"2026-09-01T18:00:00.000+09:00","venue":"エスコンフィールド北海道","region":"北海道","url":"https://ticketjam.jp/tickets/fighters/event/1040365","path":"/tickets/fighters/event/1040365","listingCount":30,"teams":["fighters","softbankhawks"]},{"id":"1040366","team":"fighters","name":"日本ハム vs ソフトバンク","startDate":"2026-09-02T18:00:00.000+09:00","venue":"エスコンフィールド北海道","region":"北海道","url":"https://ticketjam.jp/tickets/fighters/event/1040366","path":"/tickets/fighters/event/1040366","listingCount":38,"teams":["fighters","softbankhawks"]},{"id":"1040704","team":"fighters","name":"ソフトバンク vs 日本ハム","startDate":"2026-09-08T18:00:00.000+09:00","venue":"みずほPayPayドーム福岡","region":"福岡県","url":"https://ticketjam.jp/tickets/softbankhawks/event/1040704","path":"/tickets/fighters/event/1040704","listingCount":27,"teams":["fighters","softbankhawks"]},{"id":"1040705","team":"fighters","name":"ソフトバンク vs 日本ハム","startDate":"2026-09-09T18:00:00.000+09:00","venue":"みずほPayPayドーム福岡","region":"福岡県","url":"https://ticketjam.jp/tickets/softbankhawks/event/1040705","path":"/tickets/fighters/event/1040705","listingCount":21,"teams":["fighters","softbankhawks"]},{"id":"1040706","team":"fighters","name":"ソフトバンク vs 日本ハム","startDate":"2026-09-10T18:00:00.000+09:00","venue":"みずほPayPayドーム福岡","region":"福岡県","url":"https://ticketjam.jp/tickets/softbankhawks/event/1040706","path":"/tickets/fighters/event/1040706","listingCount":28,"teams":["fighters","softbankhawks"]},{"id":"1088808","team":"fighters","name":"日本ハム vs 楽天","startDate":"2026-07-25T14:00:00.000+09:00","venue":"エスコンフィールド北海道","region":"北海道","url":"https://ticketjam.jp/tickets/fighters/event/1088808","path":"/tickets/fighters/event/1088808","listingCount":91,"teams":["fighters","rakuteneagles"]},{"id":"1088809","team":"fighters","name":"日本ハム vs 楽天","startDate":"2026-07-26T13:00:00.000+09:00","venue":"エスコンフィールド北海道","region":"北海道","url":"https://ticketjam.jp/tickets/fighters/event/1088809","path":"/tickets/fighters/event/1088809","listingCount":90,"teams":["fighters","rakuteneagles"]},{"id":"1095201","team":"fighters","name":"日本ハム vs 楽天","startDate":"2026-08-07T18:00:00.000+09:00","venue":"エスコンフィールド北海道","region":"北海道","url":"https://ticketjam.jp/tickets/fighters/event/1095201","path":"/tickets/fighters/event/1095201","listingCount":37,"teams":["fighters","rakuteneagles"]},{"id":"1095202","team":"fighters","name":"日本ハム vs 楽天","startDate":"2026-08-08T15:00:00.000+09:00","venue":"エスコンフィールド北海道","region":"北海道","url":"https://ticketjam.jp/tickets/fighters/event/1095202","path":"/tickets/fighters/event/1095202","listingCount":83,"teams":["fighters","rakuteneagles"]},{"id":"1095203","team":"fighters","name":"日本ハム vs 楽天","startDate":"2026-08-09T14:00:00.000+09:00","venue":"エスコンフィールド北海道","region":"北海道","url":"https://ticketjam.jp/tickets/fighters/event/1095203","path":"/tickets/fighters/event/1095203","listingCount":53,"teams":["fighters","rakuteneagles"]},{"id":"1040728","team":"fighters","name":"楽天 vs 日本ハム","startDate":"2026-09-04T18:00:00.000+09:00","venue":"楽天モバイル 最強パーク宮城","region":"宮城県","url":"https://ticketjam.jp/tickets/rakuteneagles/event/1040728","path":"/tickets/fighters/event/1040728","listingCount":1,"teams":["fighters","rakuteneagles"]},{"id":"1040729","team":"fighters","name":"楽天 vs 日本ハム","startDate":"2026-09-05T18:00:00.000+09:00","venue":"楽天モバイル 最強パーク宮城","region":"宮城県","url":"https://ticketjam.jp/tickets/rakuteneagles/event/1040729","path":"/tickets/fighters/event/1040729","listingCount":1,"teams":["fighters","rakuteneagles"]},{"id":"1040730","team":"fighters","name":"楽天 vs 日本ハム","startDate":"2026-09-06T16:00:00.000+09:00","venue":"楽天モバイル 最強パーク宮城","region":"宮城県","url":"https://ticketjam.jp/tickets/rakuteneagles/event/1040730","path":"/tickets/fighters/event/1040730","listingCount":null,"teams":["fighters","rakuteneagles"]},{"id":"1031300","team":"fighters","name":"日本ハム vs 楽天","startDate":"2026-09-22T18:00:00.000+09:00","venue":"エスコンフィールド北海道","region":"北海道","url":"https://ticketjam.jp/tickets/fighters/event/1031300","path":"/tickets/fighters/event/1031300","listingCount":49,"teams":["fighters","rakuteneagles"]},{"id":"1031301","team":"fighters","name":"日本ハム vs 楽天","startDate":"2026-09-23T18:00:00.000+09:00","venue":"エスコンフィールド北海道","region":"北海道","url":"https://ticketjam.jp/tickets/fighters/event/1031301","path":"/tickets/fighters/event/1031301","listingCount":84,"teams":["fighters","rakuteneagles"]},{"id":"1031280","team":"fighters","name":"日本ハム vs 楽天","startDate":"2026-09-24T18:00:00.000+09:00","venue":"エスコンフィールド北海道","region":"北海道","url":"https://ticketjam.jp/tickets/fighters/event/1031280","path":"/tickets/fighters/event/1031280","listingCount":92,"teams":["fighters","rakuteneagles"]},{"id":"1040447","team":"fighters","name":"オリックス vs 日本ハム","startDate":"2026-08-14T18:00:00.000+09:00","venue":"京セラドーム大阪","region":"大阪府","url":"https://ticketjam.jp/tickets/buffaloes/event/1040447","path":"/tickets/fighters/event/1040447","listingCount":61,"teams":["fighters","buffaloes"]},{"id":"1040448","team":"fighters","name":"オリックス vs 日本ハム","startDate":"2026-08-15T14:00:00.000+09:00","venue":"京セラドーム大阪","region":"大阪府","url":"https://ticketjam.jp/tickets/buffaloes/event/1040448","path":"/tickets/fighters/event/1040448","listingCount":103,"teams":["fighters","buffaloes"]},{"id":"1040449","team":"fighters","name":"オリックス vs 日本ハム","startDate":"2026-08-16T13:00:00.000+09:00","venue":"京セラドーム大阪","region":"大阪府","url":"https://ticketjam.jp/tickets/buffaloes/event/1040449","path":"/tickets/fighters/event/1040449","listingCount":83,"teams":["fighters","buffaloes"]},{"id":"1031303","team":"fighters","name":"日本ハム vs オリックス","startDate":"2026-09-19T14:00:00.000+09:00","venue":"エスコンフィールド北海道","region":"北海道","url":"https://ticketjam.jp/tickets/fighters/event/1031303","path":"/tickets/fighters/event/1031303","listingCount":46,"teams":["fighters","buffaloes"]},{"id":"1031304","team":"fighters","name":"日本ハム vs オリックス","startDate":"2026-09-20T14:00:00.000+09:00","venue":"エスコンフィールド北海道","region":"北海道","url":"https://ticketjam.jp/tickets/fighters/event/1031304","path":"/tickets/fighters/event/1031304","listingCount":41,"teams":["fighters","buffaloes"]},{"id":"1031305","team":"fighters","name":"日本ハム vs オリックス","startDate":"2026-09-21T14:00:00.000+09:00","venue":"エスコンフィールド北海道","region":"北海道","url":"https://ticketjam.jp/tickets/fighters/event/1031305","path":"/tickets/fighters/event/1031305","listingCount":42,"teams":["fighters","buffaloes"]},{"id":"1098264","team":"fighters","name":"オリックス vs 日本ハム","startDate":"2026-09-26T14:00:00.000+09:00","venue":"京セラドーム大阪","region":"大阪府","url":"https://ticketjam.jp/tickets/buffaloes/event/1098264","path":"/tickets/fighters/event/1098264","listingCount":11,"teams":["fighters","buffaloes"]},{"id":"1040621","team":"softbankhawks","name":"楽天 vs ソフトバンク","startDate":"2026-07-31T18:00:00.000+09:00","venue":"楽天モバイル 最強パーク宮城","region":"宮城県","url":"https://ticketjam.jp/tickets/rakuteneagles/event/1040621","path":"/tickets/softbankhawks/event/1040621","listingCount":25,"teams":["softbankhawks","rakuteneagles"]},{"id":"1040622","team":"softbankhawks","name":"楽天 vs ソフトバンク","startDate":"2026-08-01T18:00:00.000+09:00","venue":"楽天モバイル 最強パーク宮城","region":"宮城県","url":"https://ticketjam.jp/tickets/rakuteneagles/event/1040622","path":"/tickets/softbankhawks/event/1040622","listingCount":37,"teams":["softbankhawks","rakuteneagles"]},{"id":"1040623","team":"softbankhawks","name":"楽天 vs ソフトバンク","startDate":"2026-08-02T16:00:00.000+09:00","venue":"楽天モバイル 最強パーク宮城","region":"宮城県","url":"https://ticketjam.jp/tickets/rakuteneagles/event/1040623","path":"/tickets/softbankhawks/event/1040623","listingCount":56,"teams":["softbankhawks","rakuteneagles"]},{"id":"1040638","team":"softbankhawks","name":"ソフトバンク vs 楽天","startDate":"2026-08-14T18:00:00.000+09:00","venue":"みずほPayPayドーム福岡","region":"福岡県","url":"https://ticketjam.jp/tickets/softbankhawks/event/1040638","path":"/tickets/softbankhawks/event/1040638","listingCount":53,"teams":["softbankhawks","rakuteneagles"]},{"id":"1040639","team":"softbankhawks","name":"ソフトバンク vs 楽天","startDate":"2026-08-15T14:00:00.000+09:00","venue":"みずほPayPayドーム福岡","region":"福岡県","url":"https://ticketjam.jp/tickets/softbankhawks/event/1040639","path":"/tickets/softbankhawks/event/1040639","listingCount":75,"teams":["softbankhawks","rakuteneagles"]},{"id":"1040640","team":"softbankhawks","name":"ソフトバンク vs 楽天","startDate":"2026-08-16T13:00:00.000+09:00","venue":"みずほPayPayドーム福岡","region":"福岡県","url":"https://ticketjam.jp/tickets/softbankhawks/event/1040640","path":"/tickets/softbankhawks/event/1040640","listingCount":42,"teams":["softbankhawks","rakuteneagles"]},{"id":"1040624","team":"softbankhawks","name":"楽天 vs ソフトバンク","startDate":"2026-09-19T14:00:00.000+09:00","venue":"楽天モバイル 最強パーク宮城","region":"宮城県","url":"https://ticketjam.jp/tickets/rakuteneagles/event/1040624","path":"/tickets/softbankhawks/event/1040624","listingCount":2,"teams":["softbankhawks","rakuteneagles"]},{"id":"1040625","team":"softbankhawks","name":"楽天 vs ソフトバンク","startDate":"2026-09-20T14:00:00.000+09:00","venue":"楽天モバイル 最強パーク宮城","region":"宮城県","url":"https://ticketjam.jp/tickets/rakuteneagles/event/1040625","path":"/tickets/softbankhawks/event/1040625","listingCount":1,"teams":["softbankhawks","rakuteneagles"]},{"id":"1040626","team":"softbankhawks","name":"楽天 vs ソフトバンク","startDate":"2026-09-21T13:00:00.000+09:00","venue":"楽天モバイル 最強パーク宮城","region":"宮城県","url":"https://ticketjam.jp/tickets/rakuteneagles/event/1040626","path":"/tickets/softbankhawks/event/1040626","listingCount":1,"teams":["softbankhawks","rakuteneagles"]},{"id":"1040641","team":"softbankhawks","name":"ソフトバンク vs 楽天","startDate":"2026-09-26T18:00:00.000+09:00","venue":"みずほPayPayドーム福岡","region":"福岡県","url":"https://ticketjam.jp/tickets/softbankhawks/event/1040641","path":"/tickets/softbankhawks/event/1040641","listingCount":32,"teams":["softbankhawks","rakuteneagles"]},{"id":"1040513","team":"softbankhawks","name":"ソフトバンク vs オリックス","startDate":"2026-07-21T18:00:00.000+09:00","venue":"みずほPayPayドーム福岡","region":"福岡県","url":"https://ticketjam.jp/tickets/softbankhawks/event/1040513","path":"/tickets/softbankhawks/event/1040513","listingCount":51,"teams":["softbankhawks","buffaloes"]},{"id":"1040514","team":"softbankhawks","name":"ソフトバンク vs オリックス","startDate":"2026-07-22T18:00:00.000+09:00","venue":"みずほPayPayドーム福岡","region":"福岡県","url":"https://ticketjam.jp/tickets/softbankhawks/event/1040514","path":"/tickets/softbankhawks/event/1040514","listingCount":58,"teams":["softbankhawks","buffaloes"]},{"id":"1040515","team":"softbankhawks","name":"ソフトバンク vs オリックス","startDate":"2026-07-23T18:00:00.000+09:00","venue":"みずほPayPayドーム福岡","region":"福岡県","url":"https://ticketjam.jp/tickets/softbankhawks/event/1040515","path":"/tickets/softbankhawks/event/1040515","listingCount":57,"teams":["softbankhawks","buffaloes"]},{"id":"1040516","team":"softbankhawks","name":"ソフトバンク vs オリックス","startDate":"2026-08-22T14:00:00.000+09:00","venue":"みずほPayPayドーム福岡","region":"福岡県","url":"https://ticketjam.jp/tickets/softbankhawks/event/1040516","path":"/tickets/softbankhawks/event/1040516","listingCount":30,"teams":["softbankhawks","buffaloes"]},{"id":"1040517","team":"softbankhawks","name":"ソフトバンク vs オリックス","startDate":"2026-08-23T13:00:00.000+09:00","venue":"みずほPayPayドーム福岡","region":"福岡県","url":"https://ticketjam.jp/tickets/softbankhawks/event/1040517","path":"/tickets/softbankhawks/event/1040517","listingCount":41,"teams":["softbankhawks","buffaloes"]},{"id":"1040812","team":"softbankhawks","name":"オリックス vs ソフトバンク","startDate":"2026-08-28T18:00:00.000+09:00","venue":"京セラドーム大阪","region":"大阪府","url":"https://ticketjam.jp/tickets/buffaloes/event/1040812","path":"/tickets/softbankhawks/event/1040812","listingCount":33,"teams":["softbankhawks","buffaloes"]},{"id":"1040813","team":"softbankhawks","name":"オリックス vs ソフトバンク","startDate":"2026-08-29T18:00:00.000+09:00","venue":"京セラドーム大阪","region":"大阪府","url":"https://ticketjam.jp/tickets/buffaloes/event/1040813","path":"/tickets/softbankhawks/event/1040813","listingCount":50,"teams":["softbankhawks","buffaloes"]},{"id":"1040814","team":"softbankhawks","name":"オリックス vs ソフトバンク","startDate":"2026-08-30T14:00:00.000+09:00","venue":"京セラドーム大阪","region":"大阪府","url":"https://ticketjam.jp/tickets/buffaloes/event/1040814","path":"/tickets/softbankhawks/event/1040814","listingCount":35,"teams":["softbankhawks","buffaloes"]},{"id":"1040815","team":"softbankhawks","name":"オリックス vs ソフトバンク","startDate":"2026-09-15T18:00:00.000+09:00","venue":"京セラドーム大阪","region":"大阪府","url":"https://ticketjam.jp/tickets/buffaloes/event/1040815","path":"/tickets/softbankhawks/event/1040815","listingCount":9,"teams":["softbankhawks","buffaloes"]},{"id":"1040816","team":"softbankhawks","name":"オリックス vs ソフトバンク","startDate":"2026-09-16T18:00:00.000+09:00","venue":"京セラドーム大阪","region":"大阪府","url":"https://ticketjam.jp/tickets/buffaloes/event/1040816","path":"/tickets/softbankhawks/event/1040816","listingCount":5,"teams":["softbankhawks","buffaloes"]},{"id":"1040817","team":"softbankhawks","name":"オリックス vs ソフトバンク","startDate":"2026-09-17T18:00:00.000+09:00","venue":"京セラドーム大阪","region":"大阪府","url":"https://ticketjam.jp/tickets/buffaloes/event/1040817","path":"/tickets/softbankhawks/event/1040817","listingCount":6,"teams":["softbankhawks","buffaloes"]},{"id":"1040818","team":"softbankhawks","name":"オリックス vs ソフトバンク","startDate":"2026-09-25T18:00:00.000+09:00","venue":"京セラドーム大阪","region":"大阪府","url":"https://ticketjam.jp/tickets/buffaloes/event/1040818","path":"/tickets/softbankhawks/event/1040818","listingCount":9,"teams":["softbankhawks","buffaloes"]},{"id":"1040518","team":"softbankhawks","name":"ソフトバンク vs オリックス","startDate":"2026-09-27T14:00:00.000+09:00","venue":"みずほPayPayドーム福岡","region":"福岡県","url":"https://ticketjam.jp/tickets/softbankhawks/event/1040518","path":"/tickets/softbankhawks/event/1040518","listingCount":28,"teams":["softbankhawks","buffaloes"]},{"id":"1040646","team":"buffaloes","name":"オリックス vs 楽天","startDate":"2026-08-03T18:00:00.000+09:00","venue":"東京ドーム","region":"東京都","url":"https://ticketjam.jp/tickets/buffaloes/event/1040646","path":"/tickets/buffaloes/event/1040646","listingCount":61,"teams":["buffaloes","rakuteneagles"]},{"id":"1040647","team":"buffaloes","name":"オリックス vs 楽天","startDate":"2026-08-05T18:00:00.000+09:00","venue":"京セラドーム大阪","region":"大阪府","url":"https://ticketjam.jp/tickets/buffaloes/event/1040647","path":"/tickets/buffaloes/event/1040647","listingCount":46,"teams":["buffaloes","rakuteneagles"]},{"id":"1040648","team":"buffaloes","name":"オリックス vs 楽天","startDate":"2026-08-06T18:00:00.000+09:00","venue":"京セラドーム大阪","region":"大阪府","url":"https://ticketjam.jp/tickets/buffaloes/event/1040648","path":"/tickets/buffaloes/event/1040648","listingCount":50,"teams":["buffaloes","rakuteneagles"]},{"id":"1040372","team":"buffaloes","name":"楽天 vs オリックス","startDate":"2026-08-11T18:00:00.000+09:00","venue":"楽天モバイル 最強パーク宮城","region":"宮城県","url":"https://ticketjam.jp/tickets/rakuteneagles/event/1040372","path":"/tickets/buffaloes/event/1040372","listingCount":23,"teams":["buffaloes","rakuteneagles"]},{"id":"1040373","team":"buffaloes","name":"楽天 vs オリックス","startDate":"2026-08-12T18:00:00.000+09:00","venue":"楽天モバイル 最強パーク宮城","region":"宮城県","url":"https://ticketjam.jp/tickets/rakuteneagles/event/1040373","path":"/tickets/buffaloes/event/1040373","listingCount":28,"teams":["buffaloes","rakuteneagles"]},{"id":"1040374","team":"buffaloes","name":"楽天 vs オリックス","startDate":"2026-08-13T18:00:00.000+09:00","venue":"楽天モバイル 最強パーク宮城","region":"宮城県","url":"https://ticketjam.jp/tickets/rakuteneagles/event/1040374","path":"/tickets/buffaloes/event/1040374","listingCount":31,"teams":["buffaloes","rakuteneagles"]},{"id":"1040649","team":"buffaloes","name":"オリックス vs 楽天","startDate":"2026-08-25T18:00:00.000+09:00","venue":"京セラドーム大阪","region":"大阪府","url":"https://ticketjam.jp/tickets/buffaloes/event/1040649","path":"/tickets/buffaloes/event/1040649","listingCount":38,"teams":["buffaloes","rakuteneagles"]},{"id":"1040650","team":"buffaloes","name":"オリックス vs 楽天","startDate":"2026-08-26T18:00:00.000+09:00","venue":"京セラドーム大阪","region":"大阪府","url":"https://ticketjam.jp/tickets/buffaloes/event/1040650","path":"/tickets/buffaloes/event/1040650","listingCount":38,"teams":["buffaloes","rakuteneagles"]},{"id":"1040651","team":"buffaloes","name":"オリックス vs 楽天","startDate":"2026-08-27T18:00:00.000+09:00","venue":"京セラドーム大阪","region":"大阪府","url":"https://ticketjam.jp/tickets/buffaloes/event/1040651","path":"/tickets/buffaloes/event/1040651","listingCount":34,"teams":["buffaloes","rakuteneagles"]},{"id":"1040375","team":"buffaloes","name":"楽天 vs オリックス","startDate":"2026-09-01T18:00:00.000+09:00","venue":"秋田県立野球場 こまちスタジアム","region":"秋田県","url":"https://ticketjam.jp/tickets/rakuteneagles/event/1040375","path":"/tickets/buffaloes/event/1040375","listingCount":null,"teams":["buffaloes","rakuteneagles"]},{"id":"1040376","team":"buffaloes","name":"楽天 vs オリックス","startDate":"2026-09-02T18:00:00.000+09:00","venue":"きたぎんボールパーク（いわて盛岡ボールパーク）","region":"岩手県","url":"https://ticketjam.jp/tickets/rakuteneagles/event/1040376","path":"/tickets/buffaloes/event/1040376","listingCount":4,"teams":["buffaloes","rakuteneagles"]},{"id":"1040652","team":"buffaloes","name":"オリックス vs 楽天","startDate":"2026-09-12T14:00:00.000+09:00","venue":"京セラドーム大阪","region":"大阪府","url":"https://ticketjam.jp/tickets/buffaloes/event/1040652","path":"/tickets/buffaloes/event/1040652","listingCount":7,"teams":["buffaloes","rakuteneagles"]}]}